Workbook

Sheet Özet
A1: Konsept Araştırması – Nexlev verisi, 9 Ekim 2026
A3: KRİTERLER
A4: • Kanal açılışı ≤ 5 ay (2026-05-09 sonrası) – Nexlev 'channelCreatedAfter' + ilk video tarihiyle çapraz kontrol edildi.
A5: • Para kazanma açık (isMonetizationEnabled = true).
A6: • Tahmini aylık AdSense geliri ≥ $1.000 (Nexlev tahmini; sponsorluk/ürün dahil değil).
A8: KAPSAM VE YÖNTEM
A9: 1) search_niche_finder_channels (query='*', yukarıdaki filtreler): Nexlev 1.137 kanal buldu. Ücretsiz plan 24 saatte 5 sorgu izin verdiği için 5 sayfa = 500 kanal çekilebildi (sayfa 1,2,3,4,6).
A10: 2) latest_discovered_faceless_niches (1.000 kanal): yaşı ≤155 gün, monetize, ≥$1.000 olan 71 kanal; 61'i yeni → toplam 561 kanal.
A11: 3) 561 kanalın her birinin son video başlıkları tek tek okunup 101 konsept kümesine elle atandı (Kanallar sayfası 'Konsept' sütunu).
A12: 4) Aday boşluklar için 13 canlı YouTube araması yapıldı (rakip sayısı + kopyaların izlenmesi) ve 1.310 güncel faceless outlier video tarandı → 'Rakip Kontrolleri' sayfası.
A13: 5) 'Konseptler' sayfasında her küme için yeni kanal sayısı/geliri formülle hesaplanır; 'Fırsatlar' sayfası puanlı öneri listesidir.
A15: ÖNEMLİ UYARILAR
... A31: Rakip Kontrolleri – yapılan YouTube aramaları ve sonuçları

Sheet Kanallar
A1: No | B1: Kanal | C1: Link | D1: Konsept kodu | E1: Konsept | F1: Dil | G1: Ülke | H1: Nexlev kategori | I1: Format | J1: Aylık gelir ($) | K1: Abone | L1: Video sayısı | M1: Ort. izlenme/video | N1: Aylık izlenme | O1: Ort. süre (dk) | P1: RPM ($) | Q1: Outlier | R1: AI içerik | S1: İlk video / yaş | T1: Kanal yaşı (gün) | U1: Kaynak | V1: Son videolar (izlenme)
A2: 1 | B2: Senju | C2: YouTube | D2: GAMING | E2: Oyun (Roblox/Minecraft/diğer) | H2: sports, soccer, youtube challenge videos | J2: 64417 | K2: 377000 | L2: 95 | M2: 172500 | N2: 24109973 | O2: 23.1 | P2: 2.67 | Q2: 2.59 | R2: Hayır | S2: 28 gün | T2: 28 | U2: latest | V2: I Did Something Nobody Has Ever Done (338,000) | They Made a Rocket League Clone...I Broke it (243,000) | We Tried the Hardest Custom Map in Rocket League (94,000) | He Sold...Again (15,000)
A3: 2 | B3: 3DVerse 12 | C3: YouTube | D3: ANIM3D | E3: 3D animasyon vitrin/derleme | H3: animation, design, software | J3: 62793 | K3: 40000 | L3: 245 | M3: 4200 | N3: 32704841 | O3: 8.2 | P3: 1.92 | Q3: 0.42 | R3: Hayır | S3: 122 gün | T3: 122 | U3: latest | V3: My 3D Animation Workflow in iClone (4,200)
A4: 3 | B4: 3D_Spectra_YT | C4: YouTube | D4: ANIM3D | E4: 3D animasyon vitrin/derleme | H4: animation, future & discoveries, tech | J4: 51309 | K4: 46000 | L4: 118 | M4: 3000 | N4: 29670317 | O4: 10.9 | P4: 1.73 | Q4: 0.3 | R4: Hayır | S4: 30 gün | T4: 30 | U4: latest | V4: Top Five 3D Animations That Broke the Internet [September Edition] (3,500) | Top 6 3D Animations That Broke the Internet [August Edition] (2,500)
A5: 4 | B5: PopDaBalloon | C5: YouTube | D5: DATING | E5: Flört şovu (Pop the Balloon) özetleri | H5: reality tv, drama, stories | J5: 47833 | K5: 33100 | L5: 238 | M5: 33450 | N5: 9680828 | O5: 23.4 | P5: 4.94 | Q5: 2 | R5: Hayır | S5: 153 gün | T5: 153 | U5: latest | V5: A Toxic Match | She Flew To Chicago And He Repaid Her With A Gold Digger Meme | Pop The Balloon (160,000) | He Manipulated And Then Ghosted Her A Week Later | Pop The Balloon or Find Love | With Arlette Amuli (140,000) | She Matched With Him and Flew to Africa...The Catchup Exposed Everything Pop The Balloon or Findlove (84,000) | A Broken Match💔 | She Did Everything Right And He Had Nothing To Give | Pop The Balloon Catchup EP86 (35,000)
A6: 5 | B6: Judge Jason | C6: YouTube | D6: COPCOURT | E6: Polis suistimali → mahkeme/dava analizi | F6: en | H6: court cases & legal proceedings | I6: commentary | J6: 46580 | K6: 63200 | L6: 26 | M6: 598730.77 | N6: 9244674 | O6: 36.9 | P6: 5.04 | Q6: 9.19 | R6: Hayır | S6: 2026-07-05 | T6: 96 | U6: search | V6: The Most Hated Cop in America FINALLY Gets Punished — 1 Million Dollar Lawsuit! (4,400,000) | Cop Pulls Over the Wrong Man — CAUGHT Lying AGAIN in Court! ($450K Lawsuit) (3,700,000) | Corrupt Cop PLANTS Evidence — His Own Bodycam BACKFIRES in Court! (1,000,000) | The Most Rotten Top Cop Family in America Finally SHUT DOWN in Court! (976,000)
A7: 6 | B7: Crazy Football | C7: YouTube | D7: SPORTS | E7: Spor haber/fan/derleme | H7: soccer, sports, news | J7: 43332 | K7: 128000 | L7: 469 | M7: 3747 | N7: 40133157 | O7: 8.6 | P7: 1.08 | Q7: 0.06 | R7: Hayır | S7: 61 gün | T7: 61 | U7: latest | V7: The Most BRUTAL FINAL in World Cup History (13,000) | Why Everyone Is Calling Argentina "Vargentina" (6,200) | Will Julian Alvarez Join Barcelona?!? (2,400) | FIFA Nightmare Begins as Argentina Starts Brawl in World Cup Final (2,000)
A8: 7 | B8: Deutsche Chroniken | C8: YouTube | D8: HISTDOC | E8: Genel tarih belgeseli | F8: de | G8: DE | H8: history | I8: documentary | J8: 42087 | K8: 43900 | L8: 503 | M8: 46400 | N8: 11999261 | O8: 24.7 | P8: 3.51 | Q8: 0.61 | R8: Evet | S8: 2026-09-06 | T8: 33 | U8: search | V8: Why did Germany lose Silesia? The full story | Documentary (386,000) | Berlin ist keine Stadt – 8 Städte, die man 1920 zusammengezwungen hat (142,000) | Deutsche Nachnamen: Was dein Name über deine Herkunft verrät | Doku (140,000) | The Morgenthau Plan: America’s Plan to Abolish Germany | Documentary (121,000)
A9: 8 | B9: The Last Day | C9: YouTube | D9: DISASTER | E9: Doğal afet / volkan / felaket senaryosu | F9: en | G9: US | H9: future & discoveries | I9: documentary | J9: 42051 | K9: 24800 | L9: 20 | M9: 533315 | N9: 9058524 | O9: 18.2 | P9: 4.64 | Q9: 12.4 | R9: Evet | S9: 2026-08-05 | T9: 65 | U9: search | V9: Nepal's 2026 Disaster Explained: The Glacier That Wiped Out a Valley (4,800,000) | What would happen If the Moon Crashed Into Earth? (1,400,000) | The Wave That Was Taller Than a Skyscraper (1,300,000) | What Would Happen If an Asteroid Hit the Ocean? (1,000,000)
A10: 9 | B10: Dr. Ares Senior | C10: YouTube | D10: SENIORHEALTH | E10: Yaşlılara doktor sağlık tavsiyesi (AI) | F10: en | G10: US | H10: health | I10: educational | J10: 34161 | K10: 75000 | L10: 40 | M10: 215030 | N10: 6888217 | O10: 24.4 | P10: 4.96 | Q10: 2.57 | R10: Evet | S10: 2026-09-05 | T10: 34 | U10: search | V10: Cardiologist Warns: This Sleeping Position Increases STROKE Risk Overnight! (1,700,000) | Cardiologist Warns: Millions Do THIS Every Morning Without Knowing the Risk! (1,100,000) | What Really Happens When You Go Under Anesthesia (905,000) | 5 Common Pills That Secretly Increase Heart Attack & Stroke Risk After 60 (670,000)
A11: 10 | B11: Underwater Earth 4K | C11: YouTube | D11: OCEAN4K | E11: 3 saatlik okyanus/doğa 4K belgesel | F11: en | G11: US | H11: travel documentary | I11: documentary | J11: 33468 | K11: 26900 | L11: 104 | M11: 69775.98 | N11: 2275607 | O11: 191.3 | P11: 14.71 | Q11: 0.79 | R11: Hayır | S11: 2026-06-05 | T11: 126 | U11: search | V11: The Deep Ocean: The Last Unknown World on Earth (3,000,000) | Mariana Trench: What Lives in the Deepest Place on Earth ? (467,000) | Drake Passage: The Most Violent Waterway on Earth (414,000) | Bermuda Triangle: The Ocean Mystery That Still Haunts the World (404,000)
A12: 11 | B12: Mystic Life Stories | C12: YouTube | D12: NDE | E12: Ölüme yakın deneyim (İsa'yı gördüm) | F12: en | G12: US | H12: christianity | I12: stories | J12: 32061 | K12: 9400 | L12: 18 | M12: 109012.76 | N12: 2881532 | O12: 49 | P12: 11.13 | Q12: 0.41 | R12: Hayır | S12: 2026-09-06 | T12: 33 | U12: search | V12: Woman DIED for 19 Minutes, Met JESUS & Revealed a SHOCKING Truth About Trump in OCT. 2026 (1,700,000) | I DIED at 95 & JESUS Exposed a SHOCKING Truth About Black People — Christian Testimony (46,000) | I'm 90 Years Old — I DIED for 8 Minutes & JESUS Revealed America's TERRIFYING Warning for Sep. 2026 (46,000) | I'm 90 Years Old— I DIED for 11 Minutes & JESUS Showed Me AMERICA 's Terrifying OCTOBER 2026 WARNING (35,000)
A13: 12 | B13: States 2050 | C13: YouTube | D13: FUTUREINV | E13: 'Amerika/Japonya/Çin'in yeni icadı herkesi şoke etti' | F13: en | G13: US | H13: future & discoveries | I13: documentary | J13: 31816 | K13: 71100 | L13: 73 | M13: 136977.4 | N13: 6800170 | O13: 23.6 | P13: 4.68 | Q13: 2.48 | R13: Hayır | S13: 2026-07-05 | T13: 96 | U13: search | V13: America's New Flying Invention Is Shocking Everyone (966,000) | America's New Humanoid Robot Is Shocking the Entire World (761,000) | America’s New Invention Could Make Oil Obsolete (747,000) | America's New Weapon Could Destroy Russia and China (628,000)
A14: 13 | B14: Crime Effect | C14: YouTube | D14: TRUECRIME | E14: Gerçek suç belgeseli (anlatı) | F14: en | G14: US | H14: crime | I14: documentary | J14: 30684 | K14: 32500 | L14: 23 | M14: 311539.13 | N14: 6671378 | O14: 25.2 | P14: 4.6 | Q14: 4.9 | R14: Hayır | S14: 2026-09-06 | T14: 33 | U14: search | V14: Texas Nurse Hits 130 MPH at Red Light... Killed 6 Including Pregnant Mom and Infant | Nicole Linton (4,200,000) | 15-Year-Old Baton Rouge Teen Vanished After Confronting 51-Year-Old Predator Over a Girl (535,000) | Her Mother Gave Him Access to Her for Money — 5-Year-Old Kamarie Holland Was Found Dead Hours Later (512,000) | Louisiana Mom Claimed Her Toddler Was Kidnapped...Hours Later, Police Found Him in a Trash Can (476,000)
A15: 14 | B15: InternetJanitor | C15: YouTube | D15: CREATORDRAMA | E15: YouTuber dramaları (MrBeast dosyaları) | F15: en | H15: internet controversies | I15: commentary | J15: 28757 | K15: 25100 | L15: 11 | M15: 704000 | N15: 7308938 | O15: 21.6 | P15: 3.93 | Q15: 45.3 | R15: Hayır | S15: 2026-09-06 | T15: 33 | U15: search | V15: The MrBeast Files Are Really Bad (3,300,000) | The Jack Doherty Files Are Really Bad (1,200,000) | The Victims of MrBeast (956,000) | The Evil Psychology Of MrBeast (536,000)
A16: 15 | B16: Secret State Files | C16: YouTube | D16: ANCIENTWHY | E16: 'Atalarımız nasıl yaşadı / neden X yapıyoruz' soruları | F16: en | H16: history | I16: documentary | J16: 26791 | K16: 46800 | L16: 86 | M16: 88924.42 | N16: 5247184 | O16: 29.4 | P16: 5.11 | Q16: 1.2 | R16: Evet | S16: 2026-07-05 | T16: 96 | U16: search | V16: Before Air Conditioning, How Did Americans Survive the Summer? (992,000) | Before Central Heating, How Did Americans Survive Freezing Winters? (939,000) | America Had No Income Tax Until 1913 — How Was the Government Funded Before That? (879,000) | American Malls Were Once Packed — So What Killed Them? (755,000)
A17: 16 | B17: Baseplate | C17: YouTube | D17: GAMING | E17: Oyun (Roblox/Minecraft/diğer) | H17: roblox, animation, gaming | J17: 26030 | K17: 590000 | L17: 182 | M17: 80000 | N17: 8142426 | O17: 21.4 | P17: 3.2 | Q17: 0.67 | R17: Hayır | S17: 61 gün | T17: 61 | U17: latest | V17: Baseplate Shorts Compilation | Roblox Animation (80,000)
A18: 17 | B18: The Silent Ruins | C18: YouTube | D18: BATTLEGRAVE | E18: Savaş alanı / isimsiz mezar arkeolojisi | F18: en | H18: history | I18: documentary | J18: 25952 | K18: 9250 | L18: 60 | M18: 76752.52 | N18: 3957658 | O18: 30.5 | P18: 6.56 | Q18: 6.76 | R18: Hayır | S18: 2026-08-05 | T18: 65 | U18: search | V18: The Bullet-Riddled Ground of the Little Bighorn Just Got Even Stranger (640,000) | Something About South Dakota's Little Bighorn Battlefield No Longer Makes Sense (516,000) | The Unmarked Graves Of Antietam Battlefield Just Got Even Stranger (412,000) | Archaeologists Unearthed Something in Louisiana That Predates the Egyptian Pyramids (376,000)
A19: 18 | B19: Yucky Stew | C19: YouTube | D19: EBIKEPOV | E19: E-bisiklet POV: ünlü mahalleleri turu | F19: en | G19: US | H19: recreation | I19: vlogs | J19: 25328 | K19: 34800 | L19: 58 | M19: 254956.52 | N19: 5782952 | O19: 20.1 | P19: 4.38 | Q19: 13.6 | R19: Hayır | S19: 2026-08-05 | T19: 65 | U19: search | V19: Riding the SECRET streets of BEL-AIR to CELEBRITY HOMES (E-Bike POV) (1,500,000) | Sunset Boulevard is Dying, Restaurants Are Out Of Business, Miles Of Vacancies & Abandoned Buildings (833,000) | Riding the SECRET streets of the HOLLYWOOD HILLS to CELEBRITY HOMES (E-Bike POV) (828,000) | I TOOK MY E-BIKE DEEP INTO HOLLYWOOD’S EXOTIC CAR STREETS (insane) (501,000)
A20: 19 | B20: Lubo | C20: YouTube | D20: GAMING | E20: Oyun (Roblox/Minecraft/diğer) | F20: fr | G20: FR | H20: minecraft | I20: gaming | J20: 23432 | K20: 71100 | L20: 230 | M20: 272266.67 | N20: 8536248 | O20: 24.1 | P20: 2.75 | Q20: 10.9 | R20: Hayır | S20: 2026-07-05 | T20: 96 | U20: search | V20: We Survived 100 Days on Create with FuzeIII (497,000) | If we say the name of a block... it disappears (481,000) | 100 Players Create 2 CIVILIZATIONS: RICH vs POOR (426,000) | Minecraft but we're blind, deaf, mute, and drunk (423,000)
A21: 20 | B21: MiniFlipThatDrama | C21: YouTube | D21: AIDRAMA | E21: AI kısa drama / 'reborn' [FULL] filmler | F21: en | G21: US | H21: theatre | I21: stories | J21: 22386 | K21: 67400 | L21: 37 | M21: 307837.84 | N21: 4926019 | O21: 85 | P21: 4.54 | Q21: 5.71 | R21: Evet | S21: 2026-07-06 | T21: 95 | U21: search | V21: [FULL] ❤️💥Human Me, Falling for the Vampire I Hate (1,600,000) | [FULL] 💥⚡️Baldur: The Outcast Son of Thunder (1,600,000) | [FULL] 🐺❤️The Alpha King’s Forbidden Luna (1,000,000) | [FULL] 🪄🔥Rise of the Mage God (1,000,000)
A22: 21 | B22: Aussie True Crime | C22: YouTube | D22: TRUECRIME | E22: Gerçek suç belgeseli (anlatı) | F22: en | H22: crime | I22: documentary | J22: 21061 | K22: 6840 | L22: 88 | M22: 31660.18 | N22: 1365231 | O22: 82.9 | P22: 15.43 | Q22: 1.56 | R22: Hayır | S22: 2026-09-06 | T22: 33 | U22: search | V22: Her missing phone exposed the k*ller's lie 📱 | Murder Calls (314,000) | The prison confession that exposed a BURIED secret | Forensic Investigators (213,000) | One tiny bloodstain solved a triple family homicide | Forensic Investigators (173,000) | One tiny clue exposed a serial k*ller 🔬 | Forensic Investigators (149,000)
A23: 22 | B23: Liliana Sun | C23: YouTube | D23: LIVINGIN | E23: 'X'te yaşam' ülke belgeseli | F23: en | G23: US | H23: travel documentary | I23: documentary | J23: 20269 | K23: 40500 | L23: 23 | M23: 1171538.5 | N23: 11039208 | O23: 34.2 | P23: 1.84 | Q23: 68.1 | R23: Hayır | S23: 2026-07-05 | T23: 96 | U23: search | V23: A unique Khanty dwelling that can withstand the most severe cold in the world. Russia. Yamal. (6,300,000) | One Family's Survival in the Endless Hottest Desert in the World. Documentary (3,000,000) | How do the northern Khanty people survive in the harsh Siberian climate of Russia? (1,000,000) | What is life like for a Mongolian family in one of the world's largest deserts? (959,000)
A24: 23 | B24: Silas Investigates | C24: YouTube | D24: TRUECRIME | E24: Gerçek suç belgeseli (anlatı) | F24: en | G24: US | H24: crime | I24: documentary | J24: 19603 | K24: 6480 | L24: 26 | M24: 67819.23 | N24: 1269169 | O24: 115.4 | P24: 15.45 | Q24: 6.62 | R24: Hayır | S24: 2026-09-05 | T24: 34 | U24: search | V24: 10 People Who VANISHED Then REAPPEARED With Strange Stories | Where Were They? (698,000) | 10 People MURDERED After Exposing GOVERNMENT Secrets | Silenced Before They Could Talk (253,000) | 10 Journalists Who DISAPPEARED Chasing ONE Story | They Knew Too Much (161,000) | FAMILIES Who VANISHED Overnight And Were NEVER Found | Where Did They Go? (99,000)
A25: 24 | B25: Nils | C25: YouTube | D25: HISTDOC | E25: Genel tarih belgeseli | F25: en | G25: US | H25: history | I25: documentary | J25: 19531 | K25: 53400 | L25: 7 | M25: 1022142.9 | N25: 4888286 | O25: 42 | P25: 4 | Q25: 21.71 | R25: Hayır | S25: 2026-08-05 | T25: 65 | U25: search | V25: The First Civilization in the World Was Rather Strange (3,300,000) | The Library of Alexandria is Weirder Than You Think (2,000,000) | The Rise and Fall of the World's Most Evil Empire (No AI) (819,000) | The Phoenicians Were Stranger Than You Think (No AI) (456,000)
A26: 25 | B26: The Unseen Earth | C26: YouTube | D26: OCEAN4K | E26: 3 saatlik okyanus/doğa 4K belgesel | F26: en | G26: US | H26: travel documentary | I26: documentary | J26: 19442 | K26: 4270 | L26: 39 | M26: 52856.36 | N26: 1440883 | O26: 180.8 | P26: 13.49 | Q26: 2.94 | R26: Hayır | S26: 2026-09-05 | T26: 34 | U26: search | V26: BLUE PLANET | A Journey Through The Living Ocean | FULL EPISODE | 4K Documentary (493,000) | COASTAL SEAS | Life, Waves and Secrets Along the World’s Shores | FULL DOCUMENTARY (416,000) | DEEP SEA CREATURES | The Strange Life Forms That Rule Earth’s Hidden Worlds | FULL DOCUMENTARY (159,000) | BLUE PLANET II | The Hidden Life That Connects Earth’s Oceans | FULL EPISODE | 4K DOCUMENTTARY (151,000)
A27: 26 | B27: Serious History Compilations | C27: YouTube | D27: HISTDOC | E27: Genel tarih belgeseli | F27: en | G27: US | H27: history | I27: compilation | J27: 19316 | K27: 20000 | L27: 10 | M27: 245200 | N27: 1811501 | O27: 120.7 | P27: 10.66 | Q27: 14.15 | R27: Hayır | S27: 2026-07-06 | T27: 95 | U27: search | V27: 2 Hours of Animated History to Fall Asleep to (NO AI) (1,100,000) | 2 Hours of People Completely Crashing Out in History (276,000) | 2 Hours of History Stories for People who HATE AI SLOP (262,000) | 2.5 Hours of the Greatest Battles in History Animated | Serious History Compilation (187,000)
A28: 27 | B28: Gilded Heart Dramas | C28: YouTube | D28: AIDRAMA | E28: AI kısa drama / 'reborn' [FULL] filmler | F28: en | G28: US | H28: life stories | I28: stories | J28: 19091 | K28: 17200 | L28: 119 | M28: 35553.31 | N28: 2433617 | O28: 84.3 | P28: 7.84 | Q28: 0.34 | R28: Evet | S28: 2026-08-06 | T28: 64 | U28: search | V28: 【FULL】Everyone Thought She Was a Mute Beggar… Until They Found Out She Was a Billionaire CEO (511,000) | 【FULL】He Dumped a Cleaner—She Married the President, Not Knowing She Was the True Heiress (380,000) | 【FULL】She Hid Her True Power… Until a Monster Army Forced Her to Reveal Herself (320,000) | 【FULL】They Humiliated His Genius Wife, Not Knowing She Was an AI Legend (311,000)
A29: 28 | B29: Dad Prevails | C29: YouTube | D29: FAMREVENGE | E29: Aile intikam hikayeleri (yaşlı ebeveyn POV) | F29: en | G29: US | H29: life stories | I29: stories | J29: 18928 | K29: 8119 | L29: 75 | M29: 18930.39 | N29: 1365718 | O29: 141.5 | P29: 13.86 | Q29: 2.56 | R29: Evet | S29: 2026-09-06 | T29: 33 | U29: search | V29: “Your Wife’s Illness Isn’t Our Problem,” My Daughter-in-Law Said — Then 23 Came to My Lake House (132,000) | My Son Abandoned Me At The Airport—Then A Wealthy Woman Whispered, "I Need A Husband. Come With Me." (118,000) | My Son Threw Me Out of His Wedding for His Bride — But What I Said Next...| Family revenge story. (77,000) | My Son Texted “My Flight Was Canceled. Happy 70th.” — Then I Saw Him at the Restaurant |Dad Prevails (64,000)
A30: 29 | B30: Grands Reportages - TF1 | C30: YouTube | D30: NEWSINV | E30: Kurumsal araştırmacı gazetecilik (re-upload) | F30: fr | G30: FR | H30: investigative documentaries | I30: documentary | J30: 18478 | K30: 34900 | L30: 143 | M30: 117088.51 | N30: 6363860 | O30: 53.2 | P30: 2.9 | Q30: 5.4 | R30: Hayır | S30: 2026-07-06 | T30: 95 | U30: search | V30: Baumettes Prison: A Daily Life Under High Tension (1,000,000) | Our exclusive immersion with the Financial BRI! (559,000) | Enquête : ils ont disparu sans laisser d'adresse ! (508,000) | Saint-Maur: Inside a High-Security Prison! (478,000)
A31: 30 | B31: The State Archive | C31: YouTube | D31: CELEB_DEATH | E31: Ünlü ölüm/miras 'son dakika' (Dolly Parton vb) | F31: en | G31: US | H31: life stories | I31: documentary | J31: 18195 | K31: 7180 | L31: 44 | M31: 60029.41 | N31: 1803343 | O31: 32.5 | P31: 10.09 | Q31: 2.79 | R31: Hayır | S31: 2026-09-05 | T31: 34 | U31: search | V31: Why Dolly Parton's Marriage With Carl Dean Was Much Nastier Than You Thought (529,000) | Dolly Parton's Childhood Was Much CRUELER Than You Thought (362,000) | Presley Gerber's Childhood Was Much CRUELER Than You Thought (257,000) | Dolly Parton Was A MONSTER Off Camera (232,000)
A32: 31 | B32: Democratic Live Trust | C32: YouTube | D32: POLITICS | E32: Siyasi tepki / haber (ABD, AB, Meksika) | F32: en | G32: US | H32: pop news & gossip | I32: commentary | J32: 18115 | K32: 9590 | L32: 47 | M32: 66066.18 | N32: 6359149 | O32: 28.1 | P32: 2.85 | Q32: 0.62 | R32: Hayır | S32: 2026-09-06 | T32: 33 | U32: search | V32: Trump ORDERS for Deportation of Jim Carrey after he HUMILIATED Him on Live Tv. (1,300,000) | Morgan Freeman TEARS Trump On Live Tv. It Broke the Internet (593,000) | SNL and Jimmy Kimmel Destroyed Trump on live. It's Hilarious... (248,000) | Don Jr Calls The Cops On Jimmy Kimmel After He EXPOSED him Live on Air. It's Hilarious (139,000)
A33: 32 | B33: Meister Carl Jung | C33: YouTube | D33: SELFHELP | E33: Stoik, Jung, psikoloji, kişisel gelişim | F33: de | G33: DE | H33: self improvement | I33: commentary | J33: 17885 | K33: 20600 | L33: 67 | M33: 39883.58 | N33: 1577186 | O33: 67.7 | P33: 11.34 | Q33: 2.5 | R33: Hayır | S33: 2026-08-06 | T33: 64 | U33: search | V33: HÖR DIR DAS VOR DEM EINSCHLAFEN AN – UND WACHE MORGEN MIT EINEM VÖLLIG NEUEN GEFÜHL AUF | Carl Jung (189,000) | Gib Salz in deine Schuhe und verändere dein Leben für immer (das uralte Geheimnis) | Carl Jung (169,000) | BITTE SO – UND DAS UNIVERSUM WIRD KEINE ANDERE WAHL HABEN, ALS DICH ZU ERHÖREN | Carl Jung (135,000) | Activate Your Vagus Nerve in 4 Minutes and Attract Everything Into Your Life | Carl Jung (129,000)
A34: 33 | B34: BBTV NEW | C34: YouTube | D34: WILDLIFE | E34: Vahşi yaşam (yaşam döngüsü, avcılar) | F34: es | G34: ES | H34: wildlife | I34: documentary | J34: 17823 | K34: 11700 | L34: 14 | M34: 405114.29 | N34: 7648821 | O34: 11.3 | P34: 2.33 | Q34: 31.3 | R34: Evet | S34: 2026-09-06 | T34: 33 | U34: search | V34: Pangolín: 99 Días Desde el Nacimiento Hasta la Supervivencia | Documental del Pangolín (1,400,000) | Halcón Peregrino: 99 Días Desde el Huevo Hasta la Supervivencia | Documental del Halcón Peregrino (849,000) | León: 100 Días Desde el Nacimiento Hasta la Supervivencia | Documental del León (676,000) | Cálao Grande: 99 Días Desde el Huevo Hasta la Supervivencia | Documental del Cálao Grande (607,000)
A35: 34 | B35: JPaniagua Docs | C35: YouTube | D35: FINANCE | E35: Kişisel finans / ekonomisi / nasıl para kazanır | F35: es | G35: MX | H35: business | I35: documentary | J35: 17434 | K35: 38200 | L35: 72 | M35: 104589.03 | N35: 6693242 | O35: 16.2 | P35: 2.6 | Q35: 1.35 | R35: Hayır | S35: 2026-07-06 | T35: 95 | U35: search | V35: How ROSS Works | The $22 BILLION Empire of Clothes and DISCOUNTS (2,900,000) | How TEMU Works | The CHINESE Giant Moving $73 Billion (601,000) | How TAKIS are made | The Mexican SNACK that conquered the United States | US$1.1 billion (508,000) | MONSTER ENERGY: The brand that turned rebellion into BUSINESS | A US$70 billion empire (477,000)
A36: 35 | B36: Bestias Míticas | C36: YouTube | D36: PREHIST | E36: Tarih öncesi / dinozor / derin zaman | F36: es | H36: wildlife | I36: documentary | J36: 16237 | K36: 11200 | L36: 14 | M36: 432050 | N36: 4830846 | O36: 21.4 | P36: 3.36 | Q36: 10.5 | R36: Evet | S36: 2026-07-06 | T36: 95 | U36: search | V36: The 12 MOST TERRIFYING prehistoric monsters in history (3,800,000) | The 42 Extinct Animals That Could Still Be Alive Today | Full Series (563,000) | These Extinct Animals Could Still Be Alive in the Amazon | Complete Series (516,000) | The 6 Prehistoric Animals Found Perfectly Frozen in Ice (341,000)
A37: 36 | B37: Kindly Sleepin' | C37: YouTube | D37: SLEEP | E37: Uyku içerikleri (tarih, bilim, oyun, sohbet) | F37: en | G37: US | H37: minecraft | I37: gaming | J37: 15278 | K37: 40500 | L37: 17 | M37: 130470.59 | N37: 1659822 | O37: 157.6 | P37: 9.2 | Q37: 6.8 | R37: Hayır | S37: 2026-09-06 | T37: 33 | U37: search | V37: Fall Asleep While I Sort 100% Of These Ducks (489,000) | Fall Asleep While I Literally Find A Needle In a Haystack (308,000) | Fall Asleep While I Clean Gross Carpets and Save The World... (299,000) | Fall Asleep While I Build A Waterpark (256,000)
A38: 37 | B38: Bagholder Association | C38: YouTube | D38: BIZFALL | E38: Marka/şirket yükseliş-çöküş (dikey nişler dahil) | F38: en | G38: US | H38: business | I38: documentary | J38: 15086 | K38: 6630 | L38: 42 | M38: 114823.76 | N38: 4041167 | O38: 16.7 | P38: 3.73 | Q38: 3.09 | R38: Hayır | S38: 2026-07-05 | T38: 96 | U38: search | V38: Doritos Is (Finally) Getting What They Deserve... (1,000,000) | Pepsi Is (Finally) Getting What They Deserve… (1,000,000) | Krispy Kreme Is (Finally) Getting What They Deserve... (646,000) | KFC Won the World. So Why Is It Losing America? (468,000)
A39: 38 | B39: Elias Stoltzfus | C39: YouTube | D39: AMISH | E39: Amish topluluğu (göç, yaşam) | F39: en | H39: culture | I39: documentary | J39: 15084 | K39: 7420 | L39: 33 | M39: 137540.85 | N39: 5944153 | O39: 18.6 | P39: 2.54 | Q39: 0.14 | R39: Evet | S39: 2026-08-06 | T39: 64 | U39: search | V39: Thousands of Amish Are Leaving Their Homes — The Reason Will SHOCK You! (3,600,000) | Where Are 400,000 Amish Moving? | The Great Amish Migration Explained (815,000) | Why the Amish Are Quietly Leaving Pennsylvania After 200 Years — The Reason Will SHOCK You! (109,000) | Why Thousands of Amish Families Are Moving — It Started With a School Bus (1,500)
A40: 39 | B40: History Unfiltered | C40: YouTube | D40: NATIVE | E40: Yerli Amerikalı portre/tarih | F40: en | G40: US | H40: history | I40: documentary | J40: 14885 | K40: 6870 | L40: 124 | M40: 123524.95 | N40: 6240889 | O40: 3.5 | P40: 2.39 | Q40: 0.79 | R40: Hayır | S40: 2026-09-15 | T40: 24 | U40: search | V40: The "Afghan Mona Lisa" in 2026: What Happened to Sharbat Gula? (2,000,000) | Wild Beauty: The New Generation of Native America 🦅🪶🌿 #NativeAmerican (179,000) | The Most Beautiful Native American Faces Portrait Collection #nativeamerican #portrait (93,000) | From War Paint to Runway: Native America Today #NativeAmerican #NativeAmericans (39,000)
A41: 40 | B41: Murph | C41: YouTube | D41: ANCIENTWHY | E41: 'Atalarımız nasıl yaşadı / neden X yapıyoruz' soruları | F41: en | G41: US | H41: biology | I41: educational | J41: 14868 | K41: 14900 | L41: 48 | M41: 75682.52 | N41: 3610890 | O41: 40.1 | P41: 4.12 | Q41: 1.5 | R41: Hayır | S41: 2026-09-06 | T41: 33 | U41: search | V41: Why Don't We Eat Duck Eggs Everywhere If Ducks Lay Almost as Fast as Chickens (1,200,000) | Why Do Predators Leave You Alone While You Sleep (520,000) | Why Don’t We Farm Rabbits on the Same Scale as Chickens (442,000) | Why Are Cats Not Afraid of Humans (194,000)
A42: 41 | B42: The Cosmographer | C42: YouTube | D42: SLEEP | E42: Uyku içerikleri (tarih, bilim, oyun, sohbet) | F42: en | G42: US | H42: space & exploration | I42: documentary | J42: 14787 | K42: 9310 | L42: 90 | M42: 15305.47 | N42: 913693 | O42: 202.8 | P42: 16.18 | Q42: 1.37 | R42: Evet | S42: 2026-08-06 | T42: 64 | U42: search | V42: The Most Advanced Civilizations That Terrify Scientists (151,000) | The 10 Scariest First Contact Scenarios That Might Actually Happen (133,000) | The 7 Scariest Theories On What Existed Before Time (130,000) | The 10 Scariest Alien Civilization Scenarios That Might Actually Be Real (79,000)
A43: 42 | B43: REDDIT HAN | C43: YouTube | D43: FAMREVENGE | E43: Aile intikam hikayeleri (yaşlı ebeveyn POV) | H43: reddit stories, stories, internet culture | J43: 14451 | K43: 25900 | L43: 693 | M43: 3627 | N43: 9789445 | O43: 25.8 | P43: 1.48 | Q43: 0.33 | R43: Hayır | S43: 30 gün | T43: 30 | U43: latest | V43: My Family Wanted Me To Stay Home Because My Sister Couldn’t Get To… (5,700) | My Parents Skipped My Spinal Surgery For My Sister’s Party—So I Finally Made Them Pay (5,600) | Dad Excluded My Kids From Vacation. I Took Them to Dubai. His Call Was PRICELESS (4,600) | My Mom Told Me She Wished She’d Aborted Me. My Dad Agreed... (4,400)
A44: 43 | B44: Rewatch TV | C44: YouTube | D44: CARTOON | E44: Çizgi film analiz/nostalji | F44: en | G44: US | H44: animation | I44: commentary | J44: 14071 | K44: 44700 | L44: 12 | M44: 555883.33 | N44: 2493694 | O44: 42.9 | P44: 5.64 | Q44: 25.3 | R44: Hayır | S44: 2026-08-05 | T44: 65 | U44: search | V44: The WORST Copycats Of Popular Cartoons (3,800,000) | The Best Crossovers in Cartoon History (1,000,000) | When A Show KILLS OFF A Character (409,000) | The Evolution of Popular Cartoons (344,000)
A45: 44 | B45: Amor Imperial Cortos | C45: YouTube | D45: AIDRAMA | E45: AI kısa drama / 'reborn' [FULL] filmler | F45: es | G45: ES | H45: life stories | I45: stories | J45: 13752 | K45: 41400 | L45: 288 | M45: 69944.79 | N45: 7111630 | O45: 70.6 | P45: 1.93 | Q45: 4.85 | R45: Evet | S45: 2026-07-06 | T45: 95 | U45: search | V45: I Married a Handsome, Cold-Hearted Hunter! He Hated Women, but Now He SPOILS Me!#260602qsB2 (555,000) | He said marrying me was his greatest shame. I was reborn and I won't marry him!#260626lsB2 (409,000) | I was pushed into the sea by my ex! THE DRAGON KING OF THE SEA SAVED ME AND I WILL MAKE THAT TRAI... (378,000) | My husband loves my sister, but her husband LOVES ME! Where is this mismatched marriage headed?# (345,000)
A46: 45 | B46: Earth Unknown | C46: YouTube | D46: LIVINGIN | E46: 'X'te yaşam' ülke belgeseli | F46: en | G46: US | H46: travel documentary | I46: documentary | J46: 13716 | K46: 7720 | L46: 50 | M46: 127797 | N46: 2291994 | O46: 79.8 | P46: 5.98 | Q46: 19.41 | R46: Hayır | S46: 2026-07-05 | T46: 96 | U46: search | V46: Living in SAUDI ARABIA: How People Live in a Country Changing Faster Than Anywhere | 4K Documentary (890,000) | Living in CHINA: How People Live in a Future Country Amid Destructive Floods | 4K Travel Documentary (582,000) | LIVING IN NEPAL: Before & After the Historic Flood | The End of Nepal? | 4K Travel Documentary (255,000) | Living in Yemen: How People Live in One of the World’s Most Dangerous Countries | 4K Documentary (171,000)
A47: 46 | B47: Stateside Stories | Tales of America | C47: YouTube | D47: USPOVERTY | E47: Görünmeyen Amerika: motel aileleri, yoksulluk belgeseli | F47: en | G47: FR | H47: society | I47: documentary | J47: 13689 | K47: 20400 | L47: 30 | M47: 219391.67 | N47: 2400032 | O47: 53 | P47: 5.7 | Q47: 6.9 | R47: Hayır | S47: 2026-08-05 | T47: 65 | U47: search | V47: America's Motel Families: Life on the Edge (1,600,000) | Inside America's Hidden Poverty Crisis: From Appalachia To LA (1,100,000) | America’s Lottery Millionaires: What Happens When You Win Big? (796,000) | America Without Limits: Guns, Food and Extreme Living (253,000)
A48: 47 | B48: The Invisible Neighbors | C48: YouTube | D48: FAMREVENGE | E48: Aile intikam hikayeleri (yaşlı ebeveyn POV) | F48: en | G48: US | H48: society | I48: documentary | J48: 13433 | K48: 11300 | L48: 48 | M48: 55161.33 | N48: 2342740 | O48: 19.6 | P48: 5.73 | Q48: 0.95 | R48: Hayır | S48: 2026-08-06 | T48: 64 | U48: search | V48: Homeless at 24, She Bought a Rusted $1 Tiny Cabin — What She Found Inside Shocked the Entire Town (961,000) | Her Husband Divorced Her at 58 and Took the House — So She Turned A Gas Station Into a Luxury Home (393,000) | Homeless at 23,He Bought a Rusted Shipping Container for $20—What He Found Inside Changed Everything (237,000) | Homeless at 21, He Bought a Rusted $100 Truck to Live In — What He Found Inside Shocked Him (218,000)
A49: 48 | B49: The Quiet Wild | C49: YouTube | D49: WILDMYSTERY | E49: Bölgesel vahşi yaşam gizemi ('X eyaletinde neyin avladığı bulundu') | F49: en | H49: wildlife | I49: documentary | J49: 13407 | K49: 7790 | L49: 91 | M49: 43515.53 | N49: 3477650 | O49: 17.2 | P49: 3.86 | Q49: 0.62 | R49: Evet | S49: 2026-08-05 | T49: 65 | U49: search | V49: Biologist Finally Found What's Hunting The Nilgai In Texas—And They're More Dangerous Than You Think (961,000) | The Joro Spider is Spreading Fast in Smoky Mountains-- Is More Dangerous Than You Think (943,000) | Biologists Just Found Out What Pennsylvania Coyotes Actually Are (248,000) | Biologist Finally Found What's Hunting Zebras in California—No One Can Explain Why. (231,000)
A50: 49 | B50: Bodycam Horizon | C50: YouTube | D50: BODYCAM | E50: Polis bodycam tutuklama | F50: en | G50: US | H50: police bodycam | I50: commentary | J50: 13383 | K50: 6950 | L50: 59 | M50: 68579.25 | N50: 3510313 | O50: 22.2 | P50: 3.81 | Q50: 5.29 | R50: Hayır | S50: 2026-09-06 | T50: 33 | U50: search | V50: She Had No License, No Insurance, No Registration — and Still Thought She Could Walk Away (1,100,000) | "You Don't Need a License to Drive" - Then Cops Find a Warrant, Ammo & Drugs in Her Car (408,000) | She Used Her Sister's Name to Dodge Cops — Then They Found a Gun in the Car | Legal Breakdown (309,000) | No License, No Ticket Signed - She Pepper Sprayed Him, Then Punched a Cop | Legal Breakdown (249,000)
A51: 50 | B51: Breakpoint | C51: YouTube | D51: DISASTER | E51: Doğal afet / volkan / felaket senaryosu | F51: en | G51: US | H51: disaster and accidents | I51: documentary | J51: 13326 | K51: 14800 | L51: 82 | M51: 73296.91 | N51: 2366773 | O51: 20.5 | P51: 5.63 | Q51: 1.45 | R51: Evet | S51: 2026-06-05 | T51: 126 | U51: search | V51: This Monster Eruption Reached The Stratosphere — And That's Not The Worst Part (695,000) | Antarctica's 'Doomsday Glacier' Just Got A Terrifying New Warning—Here's What Scientists Are Saying (622,000) | The World's Most Feared Volcano Just Roared Back To Life - And It's Terrifying (604,000) | California's Labor Day Weekend Is About To Turn Dangerous — Here's Why (441,000)
A52: 51 | B52: Moon Pulse | C52: YouTube | D52: WAR_NOW | E52: Güncel savaş (Ukrayna/İran) haber-simülasyon | F52: en | G52: US | H52: military | I52: documentary | J52: 13270 | K52: 22600 | L52: 11 | M52: 820909.09 | N52: 6093731 | O52: 16.5 | P52: 2.18 | Q52: 80.8 | R52: Hayır | S52: 2026-08-06 | T52: 64 | U52: search | V52: 30 Russians Defended the Trench — Then One Ran and Gave Them All Away: 15 Cornered in One Bunker (1,500,000) | Ukrainian Soldiers Storm a Trench Line — Then Catch a Russian Major Running for His Life (1,400,000) | Ukrainians Seized the Enemy's Radio — What They Did Next Was the End for the Russian Soldiers (1,100,000) | Two-Pronged Trench Assault: 14 Ukrainian Soldiers Clear Three Bunkers in 6 Hours (1,000,000)
A53: 52 | B53: Qumal Fafma | C53: YouTube | D53: NURSING | E53: Hemşirelik sınavı (NCLEX) eğitimi | F53: en | G53: US | H53: healthcare industry | I53: tutorial | J53: 13119 | K53: 3080 | L53: 6 | M53: 713183.33 | N53: 4690553 | O53: 3 | P53: 2.8 | Q53: 24.41 | R53: Hayır | S53: 2026-09-06 | T53: 33 | U53: search | V53: The Ultimate Guide to IM Injection Needle Sizes | NCLEX Nursing Training (2,700,000) | The Secret to Choosing the Perfect IM Injection Needle | NCLEX Nursing Masterclass (1,400,000) | IM Injection Needle Sizes Explained | NCLEX Nursing Success Guide (152,000) | Selecting the Right Needle Size for IM Injection | NCLEX & NHS Nursing Training (14,000)
A54: 53 | B54: Snapped: Dark Secrets | C54: YouTube | D54: TRUECRIME | E54: Gerçek suç belgeseli (anlatı) | F54: en | G54: US | H54: crime | I54: documentary | J54: 13044 | K54: 1830 | L54: 34 | M54: 27970.59 | N54: 1142251 | O54: 152.5 | P54: 11.42 | Q54: 3.82 | R54: Hayır | S54: 2026-09-07 | T54: 32 | U54: search | V54: Snapped NEW 2026 🕵️Shaunna Dodd ☠️ Documentary True Crime (199,000) | Snapped NEW 2026 🕵️ Sarah McLinn ☠️ Documentary True Crime (85,000) | Snapped NEW 2026 🕵️ Diane Staudte ☠️ Documentary True Crime (83,000) | Snapped NEW 2026 🕵️Shanda Crain ☠️ Documentary True Crime (80,000)
A55: 54 | B55: California Reports | C55: YouTube | D55: POLITICS | E55: Siyasi tepki / haber (ABD, AB, Meksika) | F55: en | G55: US | H55: news | I55: news | J55: 12635 | K55: 9800 | L55: 58 | M55: 98096.55 | N55: 3937851 | O55: 10.8 | P55: 3.21 | Q55: 10.44 | R55: Hayır | S55: 2026-08-05 | T55: 65 | U55: search | V55: California Mayor INDICTED As FBI Informant FLIPS & Faces 95 Years Prison Time (841,000) | The Stop Nick Shirley Act: $10,000 Fine for Exposing California Fraud? (736,000) | California AG EXPOSED As $468K VANISHES Amid FBI Bribery Probe (504,000) | California's Largest FBI Raid Ever As Mexican Mafia Empire Falls (489,000)
A56: 55 | B56: Théâtre Pêche Sucrée | C56: YouTube | D56: AIDRAMA | E56: AI kısa drama / 'reborn' [FULL] filmler | F56: fr | G56: US | H56: movies | I56: drama | J56: 12304 | K56: 15300 | L56: 76 | M56: 22749.04 | N56: 1444853 | O56: 137.1 | P56: 8.52 | Q56: 0.82 | R56: Hayır | S56: 2026-09-06 | T56: 33 | U56: search | V56: Ils entendent les pensées de leur belle-fille… et découvrent qu’elle peut prédire tous les dangers ! (337,000) | Rejected by her real father, she becomes the beloved daughter of the richest man and brings good ... (148,000) | Renaît en héritière mal-aimée, sa famille entend ses pensées et démasque la fille adoptive ! (138,000) | Tous méprisaient cette grosse fille ! Mais sa force incroyable sauve 5 enfants… ceux du PDG ! (132,000)
A57: 56 | B57: SovCit Justice | C57: YouTube | D57: COURTREACT | E57: Mahkeme salonu tepkileri (sovcit, hüküm) | F57: en | H57: court cases & legal proceedings | I57: commentary | J57: 12262 | K57: 2490 | L57: 43 | M57: 71420.74 | N57: 3102024 | O57: 21.7 | P57: 3.95 | Q57: 4.12 | R57: Hayır | S57: 2026-09-06 | T57: 33 | U57: search | V57: Cocky Teen Thinks She's Getting a Plea Deal... Gets a MASSIVE Reality Check! (2,000,000) | Sovereign Citizen REFUSES To Answer The Judge… Gets SENT STRAIGHT TO JAIL! (131,000) | Sovereign Citizen Pulls a “Fake Identity” Trick on the Judge… Gets a MASSIVE Reality Check! (114,000) | Sovereign Citizen Says He’s “Outside the Law”—Judge Delivers a BRUTAL Reality Check! (98,000)
A58: 57 | B58: The Crown Unspoken | C58: YouTube | D58: ROYALS | E58: Kraliyet ailesi (çoğu clickbait) | F58: en | G58: GB | H58: royalty | I58: news | J58: 12256 | K58: 3370 | L58: 51 | M58: 30151.88 | N58: 1924503 | O58: 26 | P58: 6.37 | Q58: 5.88 | R58: Hayır | S58: 2026-08-07 | T58: 63 | U58: search | V58: Royal Family in Shock: Archie & Lilibet’s Birth Records Exposed—Harry Left Reeling! (230,000) | MEGHAN REELS! Her First Husband Speaks Out—Shocking Truth About Archie Leaves Britain in Uproar?! (147,000) | A BOMBSHELL REVELATION!? Archie & Lilibet’s Birth Mystery Takes a Shocking Turn (120,000) | Sussexes Panic: Archie & Lilibet Removed from Succession? #ArchieHarrison #SussexFamily (60,000)
A59: 58 | B59: Overengineered | C59: YouTube | D59: MEGAPROJ | E59: Mühendislik / mega proje / tehlikeli bilim | F59: en | G59: US | H59: engineering | I59: documentary | J59: 12139 | K59: 11900 | L59: 8 | M59: 637075 | N59: 4937932 | O59: 20.8 | P59: 2.46 | Q59: 10.9 | R59: Hayır | S59: 2026-09-06 | T59: 33 | U59: search | V59: The 400 km Wall Japan Built to Stop the Sea (4,300,000) | How Egypt Is Digging a 310 km River Into the Sahara Desert (286,000) | Nepal Flood Explained: How a Glacier Became a Wall of Water (222,000) | How South Korea Built a 33 km Wall to Steal Land From the Sea (133,000)
A60: 59 | B60: Cold Line | C60: YouTube | D60: INTERROG | E60: Sorgu odası / 'polisin yakalayacağından habersiz' | F60: en | G60: SK | H60: crime | I60: documentary | J60: 12117 | K60: 4940 | L60: 9 | M60: 217700 | N60: 1851250 | O60: 30.6 | P60: 6.55 | Q60: 10.59 | R60: Hayır | S60: 2026-09-06 | T60: 33 | U60: search | V60: “Friendly” Grandpa Has No Idea Police Just Exposed His Dark Secret (1,100,000) | 70-Year-Old Grandma Has No Idea Police Are About to Arrest Her for Murder After 22 Years (643,000) | Police Hunt Down 17-Year-Old Killers After Horrific Murder Plot (114,000) | Evil Son Killed His Mother & Thought He’d Get Away With It (44,000)
A61: 60 | B61: Only Interrogations | C61: YouTube | D61: INTERROG | E61: Sorgu odası / 'polisin yakalayacağından habersiz' | F61: en | G61: CA | H61: investigative documentaries | I61: interview | J61: 12044 | K61: 9090 | L61: 75 | M61: 36694.49 | N61: 1986343 | O61: 60.5 | P61: 6.06 | Q61: 4.41 | R61: Hayır | S61: 2026-08-05 | T61: 65 | U61: search | V61: Dumb Killer Denies Video Evidence Of Her, Thinks Cops Believe Her (They Don't) (486,000) | Idiot Killer Thinks He's Helping The Police, Gets Mad When They Won't Let Him Leave (234,000) | Narcissistic Teen Kills Neighbour, Thinks He's Too Young For Jail (179,000) | Entitled Ex Panics When She Realizes She Won't Get Custody Of Her Kids (138,000)
A62: 61 | B62: Patriarch's Echo | C62: YouTube | D62: FAMREVENGE | E62: Aile intikam hikayeleri (yaşlı ebeveyn POV) | F62: en | G62: US | H62: family | I62: stories | J62: 11797 | K62: 8720 | L62: 111 | M62: 29995.5 | N62: 3129224 | O62: 36.1 | P62: 3.77 | Q62: 5 | R62: Evet | S62: 2026-09-06 | T62: 33 | U62: search | V62: “YOU’RE NOT IMPORTANT ENOUGH!” My Daughter’s Fiancé’s Father Said—Then I Canceled His Deal… (259,000) | My Daughter’s Future MIL Handed Me the $3,200 Bill—Then the Waiter Said, “Come With Me.” (216,000) | “CANCEL THE WEDDING!” My Daughter’s In-Laws Banned Me—They Didn’t Know What I Owned… (168,000) | “Get Out of My House!” My Daughter-in-Law Told My Wife—Then 30 People Stood Up (148,000)
A63: 62 | B63: Clear Horizon | C63: YouTube | D63: DEBATE | E63: Tartışma klipleri (din/kültür savaşı) | F63: en | G63: US | H63: religion | I63: commentary | J63: 11594 | K63: 1790 | L63: 3 | M63: 692733.33 | N63: 3559252 | O63: 25.8 | P63: 3.26 | Q63: 50.29 | R63: Hayır | S63: 2026-09-22 | T63: 17 | U63: search | V63: Islamist Starts CRYING After Christian Student CRUSHES Islam (1,900,000) | Islamist Debater Throws TANTRUM After Douglas Murray EXPOSES Islam (171,000) | Muslim Heckler THROWS TANTRUM After Milo Yiannopoulos Brutally HUMILIATES ISLAM With Facts (7,200)
A64: 63 | B64: Airspeed | C64: YouTube | D64: AVIATION | E64: Havacılık tarihi / kişisel uçak | F64: en | G64: CA | H64: aviation | I64: documentary | J64: 11410 | K64: 19800 | L64: 8 | M64: 573250 | N64: 3880727 | O64: 11 | P64: 2.94 | Q64: 45.15 | R64: Hayır | S64: 2026-09-05 | T64: 34 | U64: search | V64: Why Did the Spirit of St. Louis Have No Front Window? (1,800,000) | Why the Boeing 377 Failed (607,000) | Why Did America Build a Fighter with Two Cockpits? (480,000) | The Plane That First Broke the Sound Barrier (479,000)
A65: 64 | B65: Duke Family Tales | C65: YouTube | D65: DUKE | E65: Tarihi aşk AI hikaye (Dük, çiftçi, kovboy) | F65: en | G65: US | H65: royalty | I65: stories | J65: 11166 | K65: 3130 | L65: 42 | M65: 15701.76 | N65: 1027767 | O65: 66.8 | P65: 10.86 | Q65: 2.43 | R65: Evet | S65: 2026-09-06 | T65: 33 | U65: search | V65: “Tell Him I’m Your Daughter,” the Little Girl Begged the Duke — Then He Saw Who Was Chasing Her (116,000) | No One Had Sat Beside the Duke in 6 Years—Until a Little Girl Took the Empty Seat (87,000) | The Maid’s Little Girl Found the Duke Asleep—What She Did Changed Him Forever (52,000) | The Maid’s Little Girl Sang to the Comatose Duke—Then He Woke Up Asking for Her (30,000)
A66: 65 | B66: The Fatal Board | C66: YouTube | D66: BIZFALL | E66: Marka/şirket yükseliş-çöküş (dikey nişler dahil) | F66: en | G66: IT | H66: business | I66: documentary | J66: 11035 | K66: 15700 | L66: 62 | M66: 40540 | N66: 1305179 | O66: 36.2 | P66: 8.45 | Q66: 1.15 | R66: Hayır | S66: 2026-08-05 | T66: 65 | U66: search | V66: The Fascinating Story of Garmin: The $7 Billion GPS Empire That Outsmarted Google Maps (468,000) | The Tragic End of Iomega: The $7 Billion Zip Drive Giant That Ruled PC Storage Then Destroyed Itself (372,000) | The Rise and Fall of TomTom: The $6 Billion GPS Giant That Ruled Every Car, Then Lost to Google Maps (316,000) | The Rise and Fall of ATI: The Toronto Company That Beat NVIDIA to Every PC, Then Lost to AMD (147,000)
A67: 66 | B67: The Quiet Record | C67: YouTube | D67: WILDMYSTERY | E67: Bölgesel vahşi yaşam gizemi ('X eyaletinde neyin avladığı bulundu') | F67: en | H67: future & discoveries | I67: documentary | J67: 10895 | K67: 5740 | L67: 37 | M67: 77727.03 | N67: 2218684 | O67: 17.4 | P67: 4.91 | Q67: 7.06 | R67: Hayır | S67: 2026-09-05 | T67: 34 | U67: search | V67: They Saw a 115-Foot Megalodon Off Australia — And Refused to Return to Sea (668,000) | A Coast Guard Diver Surfaced White as a Sheet in 1991 (550,000) | The Real Reason Megalodon May Never Have Left the Deep — And Where It Would Hide (397,000) | The Navy Pulled Claws Out of the USS Stein in 1978 - The Last Man Who Kept It Finally Speaks (151,000)
A68: 67 | B68: Supermercado al Descubierto | C68: YouTube | D68: BRANDBUY | E68: 'Alma: bu markalar sahte/iyi olanlar' | F68: es | G68: ES | H68: retail business | I68: commentary | J68: 10801 | K68: 4870 | L68: 51 | M68: 79912.33 | N68: 1965273 | O68: 28.6 | P68: 5.5 | Q68: 0.74 | R68: Hayır | S68: 2026-09-06 | T68: 33 | U68: search | V68: 20 Foods You Will Never Buy Again After Finding Out How They Are Made (1,400,000) | 7 Marcas de AGUA que Solo la Gente TONTA Compra (630,000) | AVOID These 7 RICE Brands (Only 4 Are Safe) (625,000) | 15 Foods You Need to Stockpile Before 2026 Ends (257,000)
A69: 68 | B69: SOLO REVENGE | C69: YouTube | D69: FAMREVENGE | E69: Aile intikam hikayeleri (yaşlı ebeveyn POV) | F69: en | G69: US | H69: life stories | I69: stories | J69: 10707 | K69: 13900 | L69: 44 | M69: 37095.45 | N69: 968158 | O69: 55.6 | P69: 11.06 | Q69: 2.3 | R69: Evet | S69: 2026-08-06 | T69: 64 | U69: search | V69: My Son Bought Me A $685,000 House. Her Parents Moved Into It And I Slept In My Car |Solo Revenge (314,000) | My Daughter's Future Father-In-Law Humiliated Me For 3 Hours. I Outrank Him By...|Solo Revenge (160,000) | After I Signed $6 Million To My Kids, My Wife Said They Weren't Mine - And They Already Knew... (114,000) | I Raised My 3 Stepkids For 25 Years.Then Their Real Father Came Back & Took Everything|Solo Revenge (100,000)
A70: 69 | B70: Military Blue | C70: YouTube | D70: WAR_NOW | E70: Güncel savaş (Ukrayna/İran) haber-simülasyon | F70: en | G70: US | H70: military | I70: documentary | J70: 10643 | K70: 33300 | L70: 104 | M70: 137995.29 | N70: 4329537 | O70: 26.7 | P70: 2.46 | Q70: 5.2 | R70: Evet | S70: 2026-06-05 | T70: 126 | U70: search | V70: Ukraine Waited for Russian Ammunition Convoy to Cross a Narrow Bridge — Then BLEW It Up (978,000) | Ukraine Waited for Russian Fighter Reinforcements to Reach Crimea — Then Blew Them Up (698,000) | Ukraine Waited for Russia’s Military Convoy Bound for Crimea to Enter the Marshlands—Then Blew It Up (662,000) | Ukraine Waited for Russia’s Military Supply Train to Enter Crimea — Then Blew It Up (598,000)
A71: 70 | B71: AI Drama World TV 🎬 | C71: YouTube | D71: AIDRAMA | E71: AI kısa drama / 'reborn' [FULL] filmler | F71: en | G71: US | H71: youtube faceless / tiktok pages | I71: drama | J71: 10491 | K71: 12300 | L71: 189 | M71: 14892.05 | N71: 2054739 | O71: 108.2 | P71: 5.11 | Q71: 0.45 | R71: Evet | S71: 2026-08-06 | T71: 64 | U71: search | V71: Reborn into famine, she unlocks a space linking her to a modern market—survival gets easy! (148,000) | Exiled to the frontier, she farms her way from a disgraced wife to a legendary general’s mother. (134,000) | Exiled to the frontier, she transforms barren land—and raises a legendary war god. (108,000) | On the day of her divorce, an apocalypse boss unlocks a magical space—and a new destiny. (102,000)
A72: 71 | B72: Paz en el Tao | C72: YouTube | D72: SELFHELP | E72: Stoik, Jung, psikoloji, kişisel gelişim | F72: es | G72: ES | H72: spirituality | I72: commentary | J72: 10490 | K72: 38400 | L72: 19 | M72: 240005.26 | N72: 3232312 | O72: 33.4 | P72: 3.25 | Q72: 5.6 | R72: Evet | S72: 2026-09-06 | T72: 33 | U72: search | V72: The Law of Reversed Effort to Attract EVERYTHING: Lao Tzu (2,600,000) | The Simple Path Nobody Follows to Get Your Life in Order | Lao Tzu (377,000) | Calm Makes You Act As If You Already Had EVERYTHING You Desire (366,000) | 7 Taoist Affirmations You MUST Tell Yourself Every Morning Upon Waking To Change Your Day (353,000)
A73: 72 | B73: DOMINVORA | C73: YouTube | D73: SELFHELP | E73: Stoik, Jung, psikoloji, kişisel gelişim | F73: en | G73: US | H73: psychology | I73: commentary | J73: 10462 | K73: 3000 | L73: 52 | M73: 18556.08 | N73: 1830444 | O73: 21.9 | P73: 5.72 | Q73: 0.22 | R73: Evet | S73: 2026-09-09 | T73: 30 | U73: search | V73: Women Don't Care What You Do For Them... They Are Loyal to One Thing Only! | Robert Greene (623,000) | How to Make a Woman Choose You, Even If She Has Many Options | Robert Greene Motivational Speech (144,000) | NO CONTACT Is Not Enough | Do THIS to Crush Her Ego | Robert Greene Motivational Speech (43,000) | Women Don't Care What You Do For Them... Value One Thing Only | Robert Greene Motivational Speech (25,000)
A74: 73 | B74: Misterios Retro | C74: YouTube | D74: CARTOON | E74: Çizgi film analiz/nostalji | F74: es | G74: BR | H74: animation | I74: commentary | J74: 10410 | K74: 12100 | L74: 15 | M74: 215625 | N74: 4714285 | O74: 9.3 | P74: 2.21 | Q74: 10.1 | R74: Hayır | S74: 2026-09-07 | T74: 32 | U74: search | V74: El Final de Thundercats (1985) Que Nadie Recuerda (1,200,000) | The Mazinger Z Ending (1978) That No One Remembers (458,000) | ThunderCats: The Ending TV Didn't Dare Air (229,000) | The He-Man Finale (1983) That No One Remembers (203,000)
A75: 74 | B75: FateThread AI Anime | C75: YouTube | D75: AIDRAMA | E75: AI kısa drama / 'reborn' [FULL] filmler | F75: en | G75: US | H75: animation | I75: animation | J75: 10275 | K75: 9810 | L75: 34 | M75: 33564.71 | N75: 1141200 | O75: 137.6 | P75: 9 | Q75: 4.41 | R75: Evet | S75: 2026-09-06 | T75: 33 | U75: search | V75: 【ENG DUB】💖Accidentally Marked the Beastman President, Now He Won't Let Me Go (148,000) | 【ENG DUB】💖Sweet Little Rabbit But Actually a Top-Tier Tease,Changed Fate by Conquering the MaleLeads (142,000) | 【ENG DUB】💖Transmigrated And Unmasked: The Obsessive Male Lead Loves Me Anyway, Mutual Devotion (127,000) | 【ENG DUB】💖Transmigrated to the Stars, Spoiled by Seven Beastmen Big Shots (92,000)
A76: 75 | B76: Mundo de Aves | C76: YouTube | D76: WILDLIFE | E76: Vahşi yaşam (yaşam döngüsü, avcılar) | F76: es | G76: MX | H76: wildlife | I76: documentary | J76: 10262 | K76: 11500 | L76: 50 | M76: 269032.06 | N76: 8539525 | O76: 12.8 | P76: 1.2 | Q76: 1.85 | R76: Evet | S76: 2026-06-06 | T76: 125 | U76: search | V76: Halcón Peregrino Ciclo de vida: Del huevo al cazador del cielo a más de 300 km/h (5,800,000) | Frailecillo Atlántico Ciclo de vida: Del huevo al peligroso viaje hacia el océano (1,400,000) | Halcón Peregrino: Un Día Al Borde Del Abismo, Cazando A Más De 300 km/h Para Salvar A Sus Crías (1,100,000) | Cucal Grande Ciclo de vida: Una lucha por sobrevivir desde el primer día (1,000,000)
A77: 76 | B77: The Greatest Graves | C77: YouTube | D77: GRAVES | E77: Ünlülerin mezarları / son evleri | F77: en | G77: US | H77: history | I77: documentary | J77: 10106 | K77: 13000 | L77: 102 | M77: 33546.32 | N77: 1245682 | O77: 83.6 | P77: 8.11 | Q77: 0.7 | R77: Hayır | S77: 2026-07-05 | T77: 96 | U77: search | V77: The Most Heartbreaking Open-Casket Moments of Famous Icons (317,000) | The Tragic Graves Of Child Stars Who Were Murdered (284,000) | Graves of America's Most Infamous Outlaws (258,000) | The Most Stunning Graves of Royal Family Members (182,000)
A78: 77 | B78: Mordoze | C78: YouTube | D78: SLEEP | E78: Uyku içerikleri (tarih, bilim, oyun, sohbet) | F78: en | G78: US | H78: myths and folktales | I78: documentary | J78: 10038 | K78: 2590 | L78: 30 | M78: 35517.33 | N78: 634404 | O78: 108.4 | P78: 15.82 | Q78: 2.04 | R78: Hayır | S78: 2026-08-06 | T78: 64 | U78: search | V78: The Lore of the Nameless Things is HORRIFYING (237,000) | 3 Hours Of LOTR Lore To Fall Asleep To (223,000) | Fall Asleep To The Entire History Of Middle Earth (198,000) | The Entire Story Of Melkor (Morgoth) To Fall Asleep To (71,000)
A79: 78 | B79: When America Made Everything | C79: YouTube | D79: NOSTALGIA | E79: '1960'larda her X'te olan 25 şey' (Lost American ağı) | F79: en | G79: US | H79: history | I79: documentary | J79: 10019 | K79: 6240 | L79: 15 | M79: 70380 | N79: 1185066 | O79: 65.8 | P79: 8.45 | Q79: 7.06 | R79: Hayır | S79: 2026-09-06 | T79: 33 | U79: search | V79: 30 American Companies That Made Products That Lasted 50 Years — Then Vanished (426,000) | 30 American Factories That Once Employed Entire Towns — Now Gone Forever (175,000) | 25 Detroit Factories That Built America's Middle Class — Then Went Silent (111,000) | 25 MADE IN USA Brands Every American Family Trusted Before They Disappeared (86,000)
... A87: 86 | B87: Money Life POV | C87: YouTube | D87: FINANCE | E87: Kişisel finans / ekonomisi / nasıl para kazanır | F87: en | G87: US | H87: personal finance | I87: stories | J87: 9418 | K87: 10600 | L87: 44 | M87: 55202.27 | N87: 2202518 | O87: 16.1 | P87: 4.28 | Q87: 1.45 | R87: Evet | S87: 2026-09-06 | T87: 33 | U87: search | V87: POV: You Became the Rich Friend — Then Things Got Awkward (350,000) | POV: You Stop Chasing Status and Start Living Like Old Money (338,000) | POV: You Pay Off Your House While Everyone Else Still Has a Mortgage (245,000) | POV: You Keep the Same Car for 10 Years While Everyone Else Upgrades (226,000)
A88: 87 | B88: Paint Maniac | C88: YouTube | D88: EXPLAINED | E88: 'Her şey açıklandı' / iceberg / mitler / matematik | F88: en | H88: internet culture | I88: commentary | J88: 9216 | K88: 47400 | L88: 17 | M88: 310588.24 | N88: 2089707 | O88: 11.5 | P88: 4.41 | Q88: 28.1 | R88: Hayır | S88: 2026-06-05 | T88: 126 | U88: search | V88: The Disturbing Audio Recordings Explained (755,000) | Every Dark Web Mystery Explained (658,000) | Every Meme With a Horrific Backstory Explained (473,000) | 1 Hour of Internet Horrors (466,000)
A89: 88 | B89: Inside The Maker | C89: YouTube | D89: FACTORY | E89: Fabrika üretim süreci | F89: en | H89: engineering | I89: documentary | J89: 9214 | K89: 4880 | L89: 46 | M89: 115976.09 | N89: 5172914 | O89: 10.2 | P89: 1.78 | Q89: 2.79 | R89: Evet | S89: 2026-09-06 | T89: 33 | U89: search | V89: How India Manufactures TRILLIONS of Rupees (RBI Secret)! 💸 (1,200,000) | Inside a High-Speed Hygiene Product Factory: Pure ASMR Sanitary Napkin Production Line (1,000,000) | The Billion-Dollar Whisky Factory Process! (Perfect Mechanical ASMR) (1,000,000) | How Samsung Galaxy Phones are REALLY Made! 📱 (Satisfying Factory ASMR) (959,000)
A90: 89 | B90: Ohio Uncovered | C90: YouTube | D90: LOCALHIST | E90: Eyalet/şehir/semt tarihi, terk edilmiş yerler | F90: en | G90: GE | H90: history | I90: documentary | J90: 9080 | K90: 7750 | L90: 17 | M90: 63847.06 | N90: 1522022 | O90: 25.8 | P90: 5.97 | Q90: 7.35 | R90: Hayır | S90: 2026-09-08 | T90: 31 | U90: search | V90: 10 Places in Ohio the Mob Used to Control (426,000) | The Most Famous Person From Every Ohio County (181,000) | How Columbus's Old Money Built a Village of Mansions and Then Walled Itself In: Bexley (86,000) | Ohio's Most Redneck Towns (Yes, They Exist) (73,000)
A91: 90 | B91: Sin Coordenadas | C91: YouTube | D91: LIVINGIN | E91: 'X'te yaşam' ülke belgeseli | F91: es | G91: ES | H91: travel documentary | I91: documentary | J91: 8931 | K91: 21200 | L91: 14 | M91: 325407.14 | N91: 4344528 | O91: 31.5 | P91: 2.06 | Q91: 8.1 | R91: Hayır | S91: 2026-08-06 | T91: 64 | U91: search | V91: CONGO | The Wildest and Most Dangerous Jungle Africa Keeps Hidden | 4K Documentary (2,600,000) | IRELAND: How People Survive on Europe’s Loneliest Coast | 4K Documentary (512,000) | KENYA | A Journey into the Most Dangerous and Hidden Heart of Africa | 4K Documentary (478,000) | THE DARIÉN GAP | The Most Dangerous Jungle That Man Has Never Been Able to Tame | 4k Documentary (362,000)
A92: 91 | B92: Legends of Sport | C92: YouTube | D92: CELEB_ATAGE | E92: '72 yaşında nihayet sessizliğini bozdu' | F92: en | G92: US | H92: movie star news & gossip | I92: commentary | J92: 8821 | K92: 7360 | L92: 32 | M92: 44341.12 | N92: 1731815 | O92: 41.8 | P92: 5.09 | Q92: 3.82 | R92: Evet | S92: 2026-08-06 | T92: 64 | U92: search | V92: At 72, Oprah Finally Breaks Silence on Stedman — The Real Reason She Never Married Him (426,000) | At 84, Barbra Streisand Breaks Her Silence on James Brolin—The Marriage That Took Her From Hollywood (153,000) | At 45, Serena Williams Finally Breaks Silence on Alexis Ohanian (135,000) | What Happened to Simone Biles at 29 – Try Not to CRY When You See This (109,000)
A93: 92 | B93: Dr. Elias Senior Health | C93: YouTube | D93: SENIORHEALTH | E93: Yaşlılara doktor sağlık tavsiyesi (AI) | F93: en | G93: US | H93: health | I93: educational | J93: 8765 | K93: 57500 | L93: 44 | M93: 147527.27 | N93: 3031549 | O93: 23.6 | P93: 2.89 | Q93: 2.24 | R93: Evet | S93: 2026-09-05 | T93: 34 | U93: search | V93: NEVER Agree to This: 5 Deadly Surgeries for Seniors! (847,000) | Doctor Reveals: The #1 Best Fruit to Eat for Healthy Eyesight! (693,000) | What Time Should The Elderly Go to Bed After 70 For Better Health — Here's What Doctors Explain! (438,000) | If You Wake Up With Dry Mouth, Your Body Is Warning You! (Almost Nobody Knows This) (427,000)
A94: 93 | B94: Midnight Vows Studio | C94: YouTube | D94: AIDRAMA | E94: AI kısa drama / 'reborn' [FULL] filmler | F94: en | G94: US | H94: reality tv | I94: stories | J94: 8752 | K94: 6330 | L94: 129 | M94: 13641.36 | N94: 1394266 | O94: 80.9 | P94: 6.28 | Q94: 0.25 | R94: Evet | S94: 2026-08-06 | T94: 64 | U94: search | V94: 【Full】 They sent their adopted daughter to prison—but never found out who her real family was. (973,000) | 【Full】 He was sent to execute her — but when he saw her face — he couldn't pull the trigger (168,000) | 【FULL】His Son Threw Him Out—Then He Married a Secret Billionaire Overnight (149,000) | 【FULL】He Ignored His Wife for Seven Years, Then Found His World Empty Without Her (119,000)
A95: 94 | B95: StayAlert Interrogation | C95: YouTube | D95: INTERROG | E95: Sorgu odası / 'polisin yakalayacağından habersiz' | F95: en | H95: crime interrogations | I95: documentary | J95: 8745 | K95: 3380 | L95: 23 | M95: 54592.78 | N95: 1032108 | O95: 96.8 | P95: 8.47 | Q95: 2.74 | R95: Hayır | S95: 2026-08-06 | T95: 64 | U95: search | V95: Killer Grandma Throws 2 Year Old From Mall Walkway—Then Says She Wanted Her Gone (403,000) | Predator Therapist Confesses to Assaulting 13 Year Old—Has No Idea She’s Being Recorded (295,000) | 23 Y/O Killer Grabs for Cop’s Gun Inside Interrogation Room—Instantly Regrets It (210,000) | Killer Mom Poisons 17 Month Old Baby With Fentanyl—Thinks She’s Going Home (She Can’t) (119,000)
A96: 95 | B96: Old American Empires | C96: YouTube | D96: BIZFALL | E96: Marka/şirket yükseliş-çöküş (dikey nişler dahil) | F96: en | H96: history | I96: documentary | J96: 8716 | K96: 4250 | L96: 55 | M96: 27517.38 | N96: 1166380 | O96: 34.5 | P96: 7.47 | Q96: 1.71 | R96: Hayır | S96: 2026-08-05 | T96: 65 | U96: search | V96: Why Nobody Wants to Eat at Golden Corral Anymore (411,000) | The Rise and Fall of America's Seafood Empire: Long John Silver's (238,000) | The Rise and Fall of America's Forgotten Pie Empire: Marie Callender's (130,000) | The Rise & Fall of America's Forgotten Steakhouse Empire: Ponderosa (102,000)
A97: 96 | B97: Graceborn Wisdom | C97: YouTube | D97: PRAYER | E97: Günlük dua / tespih / motivasyon vaazı | F97: en | G97: AU | H97: christianity | I97: stories | J97: 8692 | K97: 6830 | L97: 176 | M97: 4896.15 | N97: 949276 | O97: 33 | P97: 9.16 | Q97: 1.46 | R97: Hayır | S97: 2026-09-06 | T97: 33 | U97: search | V97: HIGH COMMAND HAS EYES ON YOU—YOUR PROTECTION IS NON NEGOTIABLE 🛰️🛡️ (14,000) | CHOSEN ONES, THE STREETS AND THE FBI KNOW YOU NOW—THE FEARLESS TRUTH TELLER & UNBREAKABLE PROTEC (10,000) | CHOSEN ONES, SECRET MEETING ABOUT YOU EXPOSED—THEIR CRIMES WERE OVERHEARD AND REPORTED TO POLICE (9,700) | CHOSEN ONES, EVIDENCE DISCOVERED IN THEIR PHONE ☎️ THEIR LIES ARE EXPOSED—NOW THEY'RE FINISHED! (9,400)
A98: 97 | B98: The Domino Effect | C98: YouTube | D98: WAR_NOW | E98: Güncel savaş (Ukrayna/İran) haber-simülasyon | F98: en | G98: US | H98: news | I98: commentary | J98: 8655 | K98: 45200 | L98: 27 | M98: 324481.48 | N98: 3494762 | O98: 18.3 | P98: 2.48 | Q98: 30.2 | R98: Hayır | S98: 2026-08-05 | T98: 65 | U98: search | V98: Ukraine's GENIUS Move Is Turning Russians Against Putin (921,000) | Ukraine Is Pulling Off Something Impossible In Crimea (756,000) | Wait... Is Russia Actually about to Collapse?! (558,000) | Russia’s Succession War BEGINS… Game of Thrones, SOVIET-STYLE (529,000)
A99: 98 | B99: Bloubi | C99: YouTube | D99: GAMING | E99: Oyun (Roblox/Minecraft/diğer) | H99: minecraft, gaming, youtube challenge videos | J99: 8625 | K99: 24700 | L99: 88 | M99: 24025 | N99: 4546635 | O99: 11.1 | P99: 1.9 | Q99: 0.89 | R99: Hayır | S99: 30 gün | T99: 30 | U99: latest | V99: On a BRISÉ notre amitié à cause de ce Combat de Mobs sur Minecraft (72,000) | BEATING MINECRAFT BUT MOBS HAVE GUNS (it's impossible...) (9,100) | GAGNER en BUILD BATTLE mais SEULEMENT avec El Primo (on est nul…) (8,600) | I tried to beat Minecraft as Mario (it's impossible...) (6,400)
A100: 99 | B100: Bodycam C4 | C100: YouTube | D100: BODYCAM | E100: Polis bodycam tutuklama | F100: en | G100: US | H100: police bodycam | I100: documentary | J100: 8615 | K100: 3320 | L100: 4 | M100: 541500 | N100: 2166000 | O100: 15.9 | P100: 3.98 | Q100: 102.35 | R100: Hayır | S100: 2026-09-27 | T100: 12 | U100: search | V100: Predator Police Officer Realizes He's Doing 65 Years In Prison After Phone Search (1,400,000) | High IQ Shoplifters Use TinFoil to ByPass Security Alarm l Bodycam Analysis (476,000) | Woman Attacks BF on Airplane After Finding Out He Cheated l Airport Bodycam Analysis (220,000) | Entitled Woman Chases Airplane Because She Missed Her Flight I Airport Bodycam Analysis (70,000)
A101: 100 | B101: ClashIQ | C101: YouTube | D101: DEBATE | E101: Tartışma klipleri (din/kültür savaşı) | F101: en | G101: US | H101: activism | I101: commentary | J101: 8593 | K101: 22900 | L101: 136 | M101: 151002.84 | N101: 4024764 | O101: 14.5 | P101: 2.13 | Q101: 2.95 | R101: Hayır | S101: 2026-07-07 | T101: 94 | U101: search | V101: Jordan Peterson FORCES Feminist To Define "Toxic Masculinity" — She COMPLETELY Falls Apart (2,200,000) | Nobody Has Ever SHUT DOWN The Trans Argument On LIVE TV Like Candace Owens Did To Marc Lamont Hill (1,600,000) | Piers Morgan Puts Trans Activist On The SPOT & She CANNOT Answer One Simple Question On Live TV (1,200,000) | Nobody Has Ever DISMANTLED Feminist Logic On LIVE TV Like Andrew Wilson Did To This Entire Panel (957,000)
A102: 101 | B102: Modo Aparte | C102: YouTube | D102: BRANDBUY | E102: 'Alma: bu markalar sahte/iyi olanlar' | F102: es | H102: nutrition | I102: commentary | J102: 8539 | K102: 3670 | L102: 55 | M102: 42273.67 | N102: 1849265 | O102: 9.9 | P102: 4.62 | Q102: 0.47 | R102: Hayır | S102: 2026-09-06 | T102: 33 | U102: search | V102: The 10 WORST Sardine Brands According to Profeco (And 3 That Actually Deliver) (865,000) | Las 4 PEORES Marcas de Harina de Trigo en México (Y las 3 que SÍ Vale la Pena Comprar) (477,000) | Los 5 PEORES Jabones de Baño Según Profeco (Y 5 Que SÍ Pasaron el Laboratorio) (371,000) | The 9 WORST Olive Oil Brands Sold at the Supermarket (And 4 That Are Actually Pure) (234,000)
A103: 102 | B103: Mack | C103: YouTube | D103: ANCIENTWHY | E103: 'Atalarımız nasıl yaşadı / neden X yapıyoruz' soruları | F103: en | H103: biology | I103: educational | J103: 8476 | K103: 88600 | L103: 98 | M103: 118489.69 | N103: 1761143 | O103: 23.6 | P103: 4.81 | Q103: 0.62 | R103: Evet | S103: 2026-06-05 | T103: 126 | U103: search | V103: When Did Ancient Humans Start Smoking? (1,700,000) | Why Ancient Humans Went From Black to White? (1,100,000) | Why Did Ancient Humans Start Wearing Clothes? (992,000) | Do Wild Animals Know When a Human Is Helping Them? (809,000)
A104: 103 | B104: Drive Standard | C104: YouTube | D104: BRANDBUY | E104: 'Alma: bu markalar sahte/iyi olanlar' | F104: en | H104: automotive business | I104: commentary | J104: 8451 | K104: 21400 | L104: 21 | M104: 110796.24 | N104: 2046398 | O104: 22.8 | P104: 4.13 | Q104: 0.87 | R104: Hayır | S104: 2026-09-06 | T104: 33 | U104: search | V104: 10 Car Brands That Are Collapsing (Avoid them in 2026) (921,000) | 11 SUVs That NEVER Break Down — Buy Once, Drive FOREVER! (434,000) | Nobody Wants These 15 Trucks (Even at $15,000 OFF) (378,000) | 10 Car Brands Going Out of Business — 2 Already Shut Down (163,000)
A105: 104 | B105: Abr Media | C105: YouTube | D105: FUTUREINV | E105: 'Amerika/Japonya/Çin'in yeni icadı herkesi şoke etti' | F105: en | G105: US | H105: tech | I105: documentary | J105: 8310 | K105: 3070 | L105: 7 | M105: 118112.14 | N105: 1751098 | O105: 25.1 | P105: 4.75 | Q105: 1.79 | R105: Hayır | S105: 2026-09-22 | T105: 17 | U105: search | V105: Inside Elon Musk’s $119B TERAFAB — Nothing Like This Exists (795,000) | The Giant Robot Submarine the US Navy Just Took Delivery Of (8,000) | America’s Flying Taxis Are Shocking Everyone! (7,400) | America's New Invention Could Replace Air Conditioners Forever (6,100)
A106: 105 | B106: Imperios del Sonido | C106: YouTube | D106: BIZFALL | E106: Marka/şirket yükseliş-çöküş (dikey nişler dahil) | F106: es | H106: history | I106: documentary | J106: 8166 | K106: 16400 | L106: 51 | M106: 69803.37 | N106: 2416536 | O106: 29.2 | P106: 3.38 | Q106: 2 | R106: Hayır | S106: 2026-06-06 | T106: 125 | U106: search | V106: The Tragic History of Philips: How the Company That Invented the CD Quietly Gave Up on Sound (697,000) | The Tragic Story of the Trinitron: How Sony Invented the World's Best Screen... and Abandoned It (517,000) | The Tragic Story of JVC: How the Company That Invented VHS Lost IT ALL (359,000) | La Trágica Historia de Kenwood: Cómo el Imperio del Car Audio Japonés Terminó Vendido por Partes (345,000)
A107: 106 | B107: Secret Hollywood | C107: YouTube | D107: ROYALS | E107: Kraliyet ailesi (çoğu clickbait) | F107: en | G107: US | H107: royalty | I107: commentary | J107: 8157 | K107: 1910 | L107: 14 | M107: 92957.79 | N107: 2706986 | O107: 13 | P107: 3.01 | Q107: 7.65 | R107: Evet | S107: 2026-09-22 | T107: 17 | U107: search | V107: Princess Diana’s Final Moments: French Firefighter Shares His Experience (893,000) | Elton John on Queen Camilla: Exploring Their Royal Connection (138,000) | Princess Diana’s Former Bodyguard Shares Memories of Her Final Years (95,000) | Elton John Finally Speaks About His Memories of Princess Diana (48,000)
...

Sheet Konseptler
A1: Kod | B1: Konsept | C1: Yeni kanal sayısı | D1: Toplam aylık gelir ($) | E1: Ort. gelir/kanal ($) | F1: En yüksek kanal geliri ($) | G1: Doygunluk (yeni kanal sayısına göre) | H1: Dış kontrol (YouTube arama) | I1: Kanallar (No)
A2: AIDRAMA | B2: AI kısa drama / 'reborn' [FULL] filmler | C2: =COUNTIF(Kanallar!$D$2:$D$562,A2) -> 23 | D2: =SUMIF(Kanallar!$D$2:$D$562,A2,Kanallar!$J$2:$J$562) -> 162108 | E2: =IF(C2=0,0,D2/C2) -> 7048.1739 | F2: =_xlfn.MAXIFS(Kanallar!$J$2:$J$562,Kanallar!$D$2:$D$562,A2) -> 22386 | G2: =IF(C2>=6,"Dolu (6+)",IF(C2>=3,"Kısmen dolu (3-5)","Az rakip (1-2)")) -> Dolu (6+) | H2: — | I2: #20, #27, #44, #55, #70, #74, #93, #108, #109, #112, #126, #149, #211, #227, #269, #294, #386, #398, #507, #516, #526, #528, #560
A3: GAMING | B3: Oyun (Roblox/Minecraft/diğer) | C3: =COUNTIF(Kanallar!$D$2:$D$562,A3) -> 16 | D3: =SUMIF(Kanallar!$D$2:$D$562,A3,Kanallar!$J$2:$J$562) -> 161834 | E3: =IF(C3=0,0,D3/C3) -> 10114.625 | F3: =_xlfn.MAXIFS(Kanallar!$J$2:$J$562,Kanallar!$D$2:$D$562,A3) -> 64417 | G3: =IF(C3>=6,"Dolu (6+)",IF(C3>=3,"Kısmen dolu (3-5)","Az rakip (1-2)")) -> Dolu (6+) | H3: — | I3: #1, #16, #19, #98, #195, #201, #230, #231, #233, #293, #307, #378, #423, #442, #471, #513
A4: TRUECRIME | B4: Gerçek suç belgeseli (anlatı) | C4: =COUNTIF(Kanallar!$D$2:$D$562,A4) -> 17 | D4: =SUMIF(Kanallar!$D$2:$D$562,A4,Kanallar!$J$2:$J$562) -> 132046 | E4: =IF(C4=0,0,D4/C4) -> 7767.4118 | F4: =_xlfn.MAXIFS(Kanallar!$J$2:$J$562,Kanallar!$D$2:$D$562,A4) -> 30684 | G4: =IF(C4>=6,"Dolu (6+)",IF(C4>=3,"Kısmen dolu (3-5)","Az rakip (1-2)")) -> Dolu (6+) | H4: — | I4: #13, #21, #23, #53, #80, #116, #171, #183, #225, #309, #360, #435, #455, #493, #529, #543, #554
A5: FAMREVENGE | B5: Aile intikam hikayeleri (yaşlı ebeveyn POV) | C5: =COUNTIF(Kanallar!$D$2:$D$562,A5) -> 17 | D5: =SUMIF(Kanallar!$D$2:$D$562,A5,Kanallar!$J$2:$J$562) -> 126084 | E5: =IF(C5=0,0,D5/C5) -> 7416.7059 | F5: =_xlfn.MAXIFS(Kanallar!$J$2:$J$562,Kanallar!$D$2:$D$562,A5) -> 18928 | G5: =IF(C5>=6,"Dolu (6+)",IF(C5>=3,"Kısmen dolu (3-5)","Az rakip (1-2)")) -> Dolu (6+) | H5: — | I5: #28, #42, #47, #61, #68, #107, #128, #144, #151, #161, #190, #241, #264, #308, #370, #446, #476
A6: HISTDOC | B6: Genel tarih belgeseli | C6: =COUNTIF(Kanallar!$D$2:$D$562,A6) -> 17 | D6: =SUMIF(Kanallar!$D$2:$D$562,A6,Kanallar!$J$2:$J$562) -> 116808 | E6: =IF(C6=0,0,D6/C6) -> 6871.0588 | F6: =_xlfn.MAXIFS(Kanallar!$J$2:$J$562,Kanallar!$D$2:$D$562,A6) -> 42087 | G6: =IF(C6>=6,"Dolu (6+)",IF(C6>=3,"Kısmen dolu (3-5)","Az rakip (1-2)")) -> Dolu (6+) | H6: — | I6: #7, #24, #26, #188, #194, #251, #281, #369, #393, #401, #402, #486, #497, #503, #523, #536, #538
A7: ANIM3D | B7: 3D animasyon vitrin/derleme | C7: =COUNTIF(Kanallar!$D$2:$D$562,A7) -> 2 | D7: =SUMIF(Kanallar!$D$2:$D$562,A7,Kanallar!$J$2:$J$562) -> 114102 | E7: =IF(C7=0,0,D7/C7) -> 57051 | F7: =_xlfn.MAXIFS(Kanallar!$J$2:$J$562,Kanallar!$D$2:$D$562,A7) -> 62793 | G7: =IF(C7>=6,"Dolu (6+)",IF(C7>=3,"Kısmen dolu (3-5)","Az rakip (1-2)")) -> Az rakip (1-2) | H7: — | I7: #2, #3
A8: DISASTER | B8: Doğal afet / volkan / felaket senaryosu | C8: =COUNTIF(Kanallar!$D$2:$D$562,A8) -> 11 | D8: =SUMIF(Kanallar!$D$2:$D$562,A8,Kanallar!$J$2:$J$562) -> 92030 | E8: =IF(C8=0,0,D8/C8) -> 8366.3636 | F8: =_xlfn.MAXIFS(Kanallar!$J$2:$J$562,Kanallar!$D$2:$D$562,A8) -> 42051 | G8: =IF(C8>=6,"Dolu (6+)",IF(C8>=3,"Kısmen dolu (3-5)","Az rakip (1-2)")) -> Dolu (6+) | H8: — | I8: #8, #50, #122, #145, #193, #213, #246, #298, #374, #469, #556
A9: SPORTS | B9: Spor haber/fan/derleme | C9: =COUNTIF(Kanallar!$D$2:$D$562,A9) -> 14 | D9: =SUMIF(Kanallar!$D$2:$D$562,A9,Kanallar!$J$2:$J$562) -> 78664 | E9: =IF(C9=0,0,D9/C9) -> 5618.8571 | F9: =_xlfn.MAXIFS(Kanallar!$J$2:$J$562,Kanallar!$D$2:$D$562,A9) -> 43332 | G9: =IF(C9>=6,"Dolu (6+)",IF(C9>=3,"Kısmen dolu (3-5)","Az rakip (1-2)")) -> Dolu (6+) | H9: — | I9: #6, #115, #170, #197, #316, #406, #443, #468, #484, #487, #496, #545, #555, #558
A10: ANCIENTWHY | B10: 'Atalarımız nasıl yaşadı / neden X yapıyoruz' soruları | C10: =COUNTIF(Kanallar!$D$2:$D$562,A10) -> 12 | D10: =SUMIF(Kanallar!$D$2:$D$562,A10,Kanallar!$J$2:$J$562) -> 77399 | E10: =IF(C10=0,0,D10/C10) -> 6449.9167 | F10: =_xlfn.MAXIFS(Kanallar!$J$2:$J$562,Kanallar!$D$2:$D$562,A10) -> 26791 | G10: =IF(C10>=6,"Dolu (6+)",IF(C10>=3,"Kısmen dolu (3-5)","Az rakip (1-2)")) -> Dolu (6+) | H10: — | I10: #15, #40, #102, #143, #305, #312, #325, #362, #382, #394, #436, #518
A11: SLEEP | B11: Uyku içerikleri (tarih, bilim, oyun, sohbet) | C11: =COUNTIF(Kanallar!$D$2:$D$562,A11) -> 12 | D11: =SUMIF(Kanallar!$D$2:$D$562,A11,Kanallar!$J$2:$J$562) -> 74529 | E11: =IF(C11=0,0,D11/C11) -> 6210.75 | F11: =_xlfn.MAXIFS(Kanallar!$J$2:$J$562,Kanallar!$D$2:$D$562,A11) -> 15278 | G11: =IF(C11>=6,"Dolu (6+)",IF(C11>=3,"Kısmen dolu (3-5)","Az rakip (1-2)")) -> Dolu (6+) | H11: — | I11: #36, #41, #77, #153, #174, #177, #206, #279, #355, #391, #433, #522
A12: FUTUREINV | B12: 'Amerika/Japonya/Çin'in yeni icadı herkesi şoke etti' | C12: =COUNTIF(Kanallar!$D$2:$D$562,A12) -> 11 | D12: =SUMIF(Kanallar!$D$2:$D$562,A12,Kanallar!$J$2:$J$562) -> 73173 | E12: =IF(C12=0,0,D12/C12) -> 6652.0909 | F12: =_xlfn.MAXIFS(Kanallar!$J$2:$J$562,Kanallar!$D$2:$D$562,A12) -> 31816 | G12: =IF(C12>=6,"Dolu (6+)",IF(C12>=3,"Kısmen dolu (3-5)","Az rakip (1-2)")) -> Dolu (6+) | H12: — | I12: #12, #104, #166, #205, #207, #217, #259, #329, #365, #428, #506
A13: BIZFALL | B13: Marka/şirket yükseliş-çöküş (dikey nişler dahil) | C13: =COUNTIF(Kanallar!$D$2:$D$562,A13) -> 12 | D13: =SUMIF(Kanallar!$D$2:$D$562,A13,Kanallar!$J$2:$J$562) -> 70554 | E13: =IF(C13=0,0,D13/C13) -> 5879.5 | F13: =_xlfn.MAXIFS(Kanallar!$J$2:$J$562,Kanallar!$D$2:$D$562,A13) -> 15086 | G13: =IF(C13>=6,"Dolu (6+)",IF(C13>=3,"Kısmen dolu (3-5)","Az rakip (1-2)")) -> Dolu (6+) | H13: Golf dikeyi: tek lider (Persimmon) → DİKEYDE AÇIK | I13: #37, #65, #79, #95, #105, #287, #340, #343, #403, #407, #434, #464
... A102: MINIATURE | B102: Karton minyatür ev yapımı | C102: =COUNTIF(Kanallar!$D$2:$D$562,A102) -> 1 | D102: =SUMIF(Kanallar!$D$2:$D$562,A102,Kanallar!$J$2:$J$562) -> 1113 | E102: =IF(C102=0,0,D102/C102) -> 1113 | F102: =_xlfn.MAXIFS(Kanallar!$J$2:$J$562,Kanallar!$D$2:$D$562,A102) -> 1113 | G102: =IF(C102>=6,"Dolu (6+)",IF(C102>=3,"Kısmen dolu (3-5)","Az rakip (1-2)")) -> Az rakip (1-2) | H102: — | I102: #548
B103: TOPLAM | C103: =SUM(C2:C102) -> 561 | D103: =SUM(D2:D102) -> 3348213
B104: Doygunluk eşiği: aynı kümede son 5 ayda açılmış ve ≥$1K/ay kazanan kanal sayısı (yalnız bu veri setinde). Dış kontrol sütunu canlı YouTube aramasından elle yazıldı.

Sheet Fırsatlar
A1: Sıra | B1: Konsept / fırsat | C1: Tip | D1: Kanıt (kanal no = Kanallar sayfası) | E1: Rakip kontrolü | F1: Önerilen açı / içerik planı | G1: Risk | H1: Puan (1-10)
A2: 1 | B2: Görünmeyen Amerika – faceless yoksulluk/motel/Appalachia belgeselleri | C2: Kanıtlı boşluk (1 kanal) | D2: Stateside Stories (#46) $13.7K/ay, 20K abone, 30 video; 'America's Motel Families' 1.6M | E2: Talep devasa (Drew Binsky, RocaNews 10M+), faceless rakip neredeyse yok | F2: Arşiv/stok + harita + veri anlatımı; 'Inside America's ___' serisi: motel aileleri, karavan parkları, şirket kasabaları, Native rezervasyonlar, gıda çölleri. 40-55 dk. | G2: Stok görüntü bulmak zor; etik/hassas dil | H2: 9
A3: 2 | B3: Hobi-dikey marka yükseliş & çöküş (golf dışında) | C3: Yeni konsept (kanıtlı şablon) | D3: Persimmon Archive (#287) golf $3.5K; Lost American Footwear sneaker outlier 211K (0 abone); Mr. Watchman (#343) saat $2.8K; House of Ruin (#407) moda $2.3K; Imperios del Sonido (#105, ES) elektronik $8.2K | E3: Golf aramasında Persimmon tek lider, kopyalar 400-9K. Diğer dikeylerde bulunamadı | F3: Her dikey ayrı kanal: Olta/balıkçılık (Zebco, Abu Garcia), gitar (Gibson, Peavey), fotoğraf makinesi (Minolta, Polaroid), av tüfeği (Remington, Winchester), motosiklet (Indian, Excelsior), bisiklet (Schwinn), elektrikli alet (Craftsman), karavan (Winnebago). 55+ erkek hobi kitlesi = yüksek RPM. | G3: The Fall Files ile örtüşme riski – dikey hobi kitlesine odaklanarak ayrıştır | H3: 9
A4: 3 | B4: Eyalet-özel tarih kanalı ('Ohio Uncovered' şablonu) | C4: Kanıtlı boşluk (1 kanal) | D4: Ohio Uncovered (#89) $9.1K/ay, sadece 17 video, 7K abone ('10 Places in Ohio the Mob Used to Control' 426K) | E4: Aranmadı; veri setinde başka eyalet kanalı yok | F4: Pennsylvania/Michigan/Texas/Kentucky Uncovered: mafya yerleri, her ilçenin en ünlü kişisi, eski para semtleri, kaybolan kasabalar. Yerel gurur = paylaşım. | G4: Her eyalet kitlesi sınırlı; çok kanal ağı kurulabilir | H4: 8
A5: 4 | B5: Kore / Vietnam / unutulan savaşlar belgeseli | C5: Yeni konsept | D5: 38th Parallel Files (outlier, 0K abone, 'Pork Chop Hill 1953' 286K); WW2 kümesinde 14 yeni kanal = WW2 doymuş | E5: WW2 kalabalık; Kore Savaşı için tek outlier kanal görüldü | F5: Kore Savaşı, Vietnam, Falkland, Boer, Rus-Japon savaşı. WW2'deki 'Japonlar güldü – ta ki...' şablonunu Kore'ye taşı. | G5: Arşiv görüntü kısıtlı | H5: 8
A6: 5 | B6: E-bisiklet POV ünlü mahalleleri (başka şehirler) | C6: Kanıtlı boşluk (1 kanal) | D6: Yucky Stew (#18) $25.3K/ay, 34K abone, 58 video | E6: AÇIK – YouTube aramasında tek ciddi kanal | F6: Miami (Star Island), Nashville country yıldız evleri, Atlanta, Hamptons, Londra Kensington, Dubai. 4K POV çekim. | G6: Faceless ama yerinde çekim gerektirir (AI ile yapılamaz) | H6: 8
A7: 6 | B7: Hemşirelik / sağlık sınavı hazırlık (NCLEX, EMT, CNA) | C7: Kanıtlı boşluk (1 kanal) | D7: Qumal Fafma (#52) $13.1K/ay, sadece 6 video, 2.7M izlenmeli video | E7: Aranmadı; veri setinde tek | F7: Animasyonlu ilaç dozları, iğne boyutları, laboratuvar değerleri ezber teknikleri. Eğitim = çok yüksek RPM + evergreen. | G7: Doğruluk sorumluluğu (uzman kontrolü şart) | H7: 8
A8: 7 | B8: Klasik TV derin bilgi (55+ kitle) | C8: Yeni konsept | D8: Curtain Cut outlier ('The REAL Reason the Professor Never Fixed the Boat' 437K, 0 abone; '70'lerin unutulan süper kahraman dizileri' 234K); Rewatch TV (#43) $14K; Rewind Facts outlier | E8: Klasik TV 'kötü yıldız' listeleri dolu (#179,#303) ama dizi-içi lore/trivia boş | F8: Gilligan's Island, Bonanza, M*A*S*H, Andy Griffith, Twilight Zone: 'gerçek sebep', 'çekim arkası', 'silinen sahne'. TV izleyen yaşlı ABD kitlesi. | G8: Klip telif riski – görsel AI/still ile | H8: 8
A9: 8 | B9: Kapalı topluluklar (Amish'in ötesi) | C9: Komşu boşluk | D9: Elias Stoltzfus (#38) $15K/ay, 7K abone; Amish videosu 3.7M | E9: Amish konusu kopyalarla doldu (10+ kanal ama 0-2K izlenme). Mennonit/Hutterit/Hasidik/FLDS için kanal görülmedi | F9: Hutterites, Mennonitler, Old Order, Hasidik Yahudiler, Doukhobor, Shakers tarihi. 'Neden göç ediyorlar / nasıl para kazanıyorlar'. | G9: Hassas dini konular; saygılı ton | H9: 7
A10: 9 | B10: Savaş alanı mezar arkeolojisi (İç Savaş dışı) | C10: Kısmen açık | D10: The Silent Ruins (#17) $26K/ay, 9K abone | E10: Antietam/Gettysburg kopyalandı (kopyalar 4-36K alıyor) | F10: WW1 Batı Cephesi, Pasifik adaları, Vahşi Batı katliam alanları, gemi enkazı mezarları. 'Just Got Even Stranger' kalıbı. | G10: Kopya kanallar hızla geliyor | H10: 7
A11: 10 | B11: İspanyolca/Almanca/Fransızca port (dil arbitrajı) | C11: Yeni konsept | D11: ES/DE/FR kanalları veri setinin %18'i; ES'de 'marka alma' (#67 $10.8K, #101 $8.5K), DE'de soyadı (#336) ve tarih (#7 $42K!) | E11: Rakip yoğunluğu EN'e göre çok düşük | F11: Kanıtlı EN formatlarını DE/FR'ye taşı: Görünmeyen Almanya, Alman marka çöküşleri (#434 var), Fransız 'Lost' nostalji (#464 var). Deutsche Chroniken (#7) $42K/ay = DE tarih çok kârlı. | G11: Ana dil seviyesinde senaryo gerekir | H11: 7
A12: 11 | B12: Ölüme yakın deneyim (NDE) anlatıları | C12: Kanıtlı (az kanal) – dış kontrol yapılmadı | D12: Mystic Life Stories (#11) $32K/ay (9K abone, 1 video 1.7M), When You Die (#286) $3.6K | E12: Aranmadı (kota) – ilk kontrol edilmesi gereken | F12: Yaşlı anlatıcı + 'X dakika öldüm ve gördüm' hikayeleri; Hristiyan kitle + uyku/uzun format. İspanyolca versiyonu da düşünülebilir. | G12: Gelir tek bir viral videoya dayanıyor olabilir | H12: 7
A13: 12 | B13: Cozy kamu malı dedektif uyku gizemleri (Holmes dışı) | C13: Kısmen açık | D13: Holmes Legacy (#452) $1.9K, 221B Archive (#453) $1.9K – ikisi de 1-3K abone | E13: Holmes için 4-5 küçük kanal; Father Brown/Dupin/Thorndyke için yok | F13: Father Brown, Auguste Dupin, Dr. Thorndyke, Sexton Blake, Craig Kennedy – 2 saatlik uyku gizemleri. | G13: Gelir düşük-orta; uzun video üretim maliyeti | H13: 6
... A23: 22 | B23: Kamyoncu dünyası | C23: Kanıtlı boşluk (1 kanal) | D23: Trucker Life (#392) $2.5K ('20 U.S. Rest Areas So DANGEROUS' 475K) | E23: Aranmadı | F23: Tehlikeli yollar, köprüler, kamyoncu efsaneleri, kayıp kamyon hikayeleri. | G23: Düşük-orta gelir | H23: 5
B25: Puan = talep kanıtı (kanal geliri/outlier) + rakip azlığı + faceless/AI üretilebilirlik + RPM tahmini; benim değerlendirmem (sarı hücreler değiştirilebilir).

Sheet Rakip Kontrolleri
A1: Arama sorgusu | B1: Tarih filtresi | C1: Bulgular | D1: Sonuç
A2: riding bike through celebrity neighborhoods homes | B2: Yıl | C2: Yucky Stew tek ciddi oyuncu (1.6M, 857K, 514K); diğerleri vlog/alakasız. | D2: AÇIK – tek kanal
A3: Sherlock Holmes mystery full story sleep | B3: Ay | C3: What If SleepStorian (1-7K), 221B Stories (15K), Watson's Journal (~0), Midnight Time Traveller (2K). Toplam ~396 sonuç. | D3: KISMEN AÇIK – 4-5 küçük kanal, kimse büyümemiş
A4: Amish leaving why | B4: Ay | C4: Elias Stoltzfus 3.7M; Amish Faith Today 86-105K; 10+ kopya kanal 0-2K izlenme. | D4: KOPYA DOLU – orijinal kazanıyor, kopyalar ölü
A5: battlefield unmarked graves just got even | B5: Yıl | C5: Silent Ruins 455K; Below the Floor 36K, Relics of America 17K, Redline 4K; birebir kopyalar. | D5: KISMEN AÇIK – kopyalar 17-36K alabiliyor
A6: what happened to his children after he was overthrown | B6: Yıl | C6: After the Crown 675K; ~15 kopya (RU/DE/ES/AR çeviri dahil) çoğu <3K. | D6: KOPYA DOLU – kazanan tek
A7: corrupt cop caught lying in court lawsuit judge | B7: Ay (uzun) | C7: Justice Brief 382K, Court Unsealed 15K; 15+ kopya 0-500 izlenme (aynı başlıklar). | D7: DOLU – kazanan-hepsini-alır
A8: America's motel families poverty documentary | B8: Yıl (uzun) | C8: Talep çok yüksek (Drew Binsky 9.8M/14M, RocaNews 12M, Witness 560K) ama faceless kanal yok denecek kadar az (Professor Maple 96 izlenme). | D8: AÇIK – talep var, faceless arz yok
A9: 60 year old carpenter wood trick genius idea | B9: Ay | C9: Maker Wood Master (797K), Wood Creation (286K), Unknown Tricks (1.4M), Clever Maker (212K), DIY WoodSpark, woodworking Tips – ~6 kanal, hepsi izlenme alıyor. | D9: KISMEN DOLU – ama yeni giren de izlenme alıyor
A10: deep ocean 4K documentary 3 hours relaxing | B10: Ay (uzun) | C10: Underwater Earth 4K 70K; onlarca yeni kanal 12-2.000 izlenme. | D10: DOLU
A11: why nobody wants to visit anymore | B11: Ay | C11: Forgotten British Cities 97K, MrHousing 90K, The Faded Coast 67K, Grand Manors 20K, Industrial South 25K, After The Prime 103K – ~8 kanal, çoğu iyi gidiyor. | D11: KISMEN AÇIK – format büyüyor, bölgeler paylaşılıyor
A12: the economics of owning a | B12: Ay | C12: THE OWNERS, Lucas Economics, Mr. Finance, Ownership Lab, Cost Anatomy, Useless Money... 15+ kanal, çoğu <10K. | D12: DOLU
... A15: faceless_outliers (Eylül 2026+, <20K abone, >200K izlenme, EN, uzun) | B15: Eylül-Ekim | C15: 1.310 outlier video. Dikkat çekenler: Curtain Cut (0 abone, Gilligan's Island 437K), 38th Parallel Files (Kore Savaşı 286K), Lost American Footwear (sneaker marka çöküşü 211K), Nature's Tether (bölgesel vahşi yaşam 445K), Mr Isles (İngiliz emekliler 209K), Jonathan Funk (Social Security 501K), Vintage Trains (204K). | D15: Yeni konsept sinyalleri
